{"CH21AA": ["53.196876", "-2.894568", "E06000050", "Cheshire West and Chester", "11,969", "4"], "CH21AB": ["53.198963", "-2.894774", "E06000050", "Cheshire West and Chester", "23,480", "8"], "CH21AD": ["53.212302", "-2.899620", "E06000050", "Cheshire West and Chester", "30,637", "10"], "CH21AE": ["53.198120", "-2.894099", "E06000050", "Cheshire West and Chester", "11,969", "4"], "CH21AF": ["53.197898", "-2.894049", "E06000050", "Cheshire West and Chester", "11,969", "4"], "CH21AG": ["53.213266", "-2.900225", "E06000050", "Cheshire West and Chester", "30,637", "10"], "CH21AH": ["53.196997", "-2.894076", "E06000050", "Cheshire West and Chester", "11,969", "4"], "CH21AJ": ["53.199586", "-2.895551", "E06000050", "Cheshire West and Chester", "23,480", "8"], "CH21AL": ["53.200675", "-2.895409", "E06000050", "Cheshire West and Chester", "11,969", "4"], "CH21AN": ["53.203222", "-2.893755", "E06000050", "Cheshire West and Chester", "26,310", "9"], "CH21AP": ["53.203656", "-2.894618", "E06000050", "Cheshire West and Chester", "26,310", "9"], "CH21AQ": ["53.200055", "-2.894109", "E06000050", "Cheshire West and Chester", "11,969", "4"], "CH21AR": ["53.201207", "-2.895180", "E06000050", "Cheshire West and Chester", "26,310", "9"], "CH21AS": ["53.205136", "-2.893855", "E06000050", "Cheshire West and Chester", "21,965", "7"], "CH21AT": ["53.205164", "-2.894963", "E06000050", "Cheshire West and Chester", "26,310", "9"], "CH21AU": ["53.209023", "-2.894565", "E06000050", "Cheshire West and Chester", "21,965", "7"], "CH21AW": ["53.203708", "-2.894575", "E06000050", "Cheshire West and Chester", "26,310", "9"], "CH21AX": ["53.211183", "-2.895388", "E06000050", "Cheshire West and Chester", "30,637", "10"], "CH21AY": ["53.210183", "-2.896865", "E06000050", "Cheshire West and Chester", "21,965", "7"], "CH21AZ": ["53.214424", "-2.897208", "E06000050", "Cheshire West and Chester", "30,637", "10"], "CH21BA": ["53.215576", "-2.896978", "E06000050", "Cheshire West and Chester", "30,637", "10"], "CH21BB": ["53.216717", "-2.895803", "E06000050", "Cheshire West and Chester", "30,637", "10"], "CH21BD": ["53.216973", "-2.895031", "E06000050", "Cheshire West and Chester", "30,637", "10"], "CH21BE": ["53.202750", "-2.894434", "E06000050", "Cheshire West and Chester", "26,310", "9"], "CH21BF": ["53.213631", "-2.898629", "E06000050", "Cheshire West and Chester", "30,637", "10"], "CH21BG": ["53.213803", "-2.900505", "E06000050", "Cheshire West and Chester", "30,637", "10"], "CH21BH": ["53.198735", "-2.895174", "E06000050", "Cheshire West and Chester", "23,480", "8"], "CH21BJ": ["53.210172", "-2.898362", "E06000050", "Cheshire West and Chester", "21,965", "7"], "CH21BL": ["53.214359", "-2.899857", "E06000050", "Cheshire West and Chester", "30,637", "10"], "CH21BN": ["53.214090", "-2.897276", "E06000050", "Cheshire West and Chester", "30,637", "10"], "CH21BP": ["53.206983", "-2.900481", "E06000050", "Cheshire West and Chester", "21,965", "7"], "CH21BQ": ["53.211544", "-2.898825", "E06000050", "Cheshire West and Chester", "30,637", "10"], "CH21BR": ["53.207548", "-2.895912", "E06000050", "Cheshire West and Chester", "21,965", "7"], "CH21BS": ["53.211428", "-2.890302", "E06000050", "Cheshire West and Chester", "21,965", "7"], "CH21BT": ["53.210883", "-2.889812", "E06000050", "Cheshire West and Chester", "21,965", "7"], "CH21BU": ["53.210015", "-2.892908", "E06000050", "Cheshire West and Chester", "21,965", "7"], "CH21BW": ["53.213425", "-2.898490", "E06000050", "Cheshire West and Chester", "30,637", "10"], "CH21BX": ["53.212056", "-2.894074", "E06000050", "Cheshire West and Chester", "30,637", "10"], "CH21BY": ["53.211891", "-2.894475", "E06000050", "Cheshire West and Chester", "30,637", "10"], "CH21BZ": ["53.213674", "-2.895007", "E06000050", "Cheshire West and Chester", "30,637", "10"], "CH21DA": ["53.209388", "-2.893884", "E06000050", "Cheshire West and Chester", "30,637", "10"], "CH21DB": ["53.210562", "-2.894267", "E06000050", "Cheshire West and Chester", "30,637", "10"], "CH21DD": ["53.212893", "-2.895095", "E06000050", "Cheshire West and Chester", "30,637", "10"], "CH21DE": ["53.211497", "-2.888282", "E06000050", "Cheshire West and Chester", "21,965", "7"], "CH21DF": ["53.210381", "-2.886088", "E06000050", "Cheshire West and Chester", "21,965", "7"], "CH21DG": ["53.210978", "-2.886789", "E06000050", "Cheshire West and Chester", "21,965", "7"], "CH21DH": ["53.212438", "-2.886280", "E06000050", "Cheshire West and Chester", "21,965", "7"], "CH21DJ": ["53.216164", "-2.889247", "E06000050", "Cheshire West and Chester", "30,637", "10"], "CH21DL": ["53.217368", "-2.888194", "E06000050", "Cheshire West and Chester", "27,465", "9"], "CH21DN": ["53.217608", "-2.888454", "E06000050", "Cheshire West and Chester", "27,465", "9"], "CH21DP": ["53.198125", "-2.894981", "E06000050", "Cheshire West and Chester", "23,480", "8"], "CH21DQ": ["53.211669", "-2.885785", "E06000050", "Cheshire West and Chester", "21,965", "7"], "CH21DR": ["53.210488", "-2.898129", "E06000050", "Cheshire West and Chester", "21,965", "7"], "CH21DS": ["53.212048", "-2.887919", "E06000050", "Cheshire West and Chester", "21,965", "7"], "CH21DT": ["53.215000", "-2.902971", "E06000050", "Cheshire West and Chester", "30,637", "10"], "CH21DU": ["53.211559", "-2.898826", "E06000050", "Cheshire West and Chester", "30,637", "10"], "CH21DW": ["53.212672", "-2.887498", "E06000050", "Cheshire West and Chester", "21,965", "7"], "CH21DX": ["53.212587", "-2.886747", "E06000050", "Cheshire West and Chester", "21,965", "7"], "CH21DY": ["53.213957", "-2.901811", "E06000050", "Cheshire West and Chester", "30,637", "10"], "CH21DZ": ["53.214612", "-2.899638", "E06000050", "Cheshire West and Chester", "30,637", "10"], "CH21EA": ["53.216746", "-2.894456", "E06000050", "Cheshire West and Chester", "30,637", "10"], "CH21EB": ["53.218291", "-2.893395", "E06000050", "Cheshire West and Chester", "30,637", "10"], "CH21ED": ["53.218622", "-2.887202", "E06000050", "Cheshire West and Chester", "30,637", "10"], "CH21EE": ["53.218335", "-2.886297", "E06000050", "Cheshire West and Chester", "30,637", "10"], "CH21EF": ["53.218849", "-2.894440", "E06000050", "Cheshire West and Chester", "30,637", "10"], "CH21EG": ["53.218161", "-2.891550", "E06000050", "Cheshire West and Chester", "30,637", "10"], "CH21EH": ["53.219332", "-2.891200", "E06000050", "Cheshire West and Chester", "30,637", "10"], "CH21EJ": ["53.219639", "-2.892225", "E06000050", "Cheshire West and Chester", "30,637", "10"], "CH21EL": ["53.219571", "-2.888090", "E06000050", "Cheshire West and Chester", "27,465", "9"], "CH21EN": ["53.219821", "-2.890671", "E06000050", "Cheshire West and Chester", "30,637", "10"], "CH21EP": ["53.220686", "-2.890449", "E06000050", "Cheshire West and Chester", "30,637", "10"], "CH21EQ": ["53.218929", "-2.891012", "E06000050", "Cheshire West and Chester", "30,637", "10"], "CH21ER": ["53.217686", "-2.886433", "E06000050", "Cheshire West and Chester", "27,465", "9"], "CH21ES": ["53.218632", "-2.888670", "E06000050", "Cheshire West and Chester", "30,637", "10"], "CH21ET": ["53.218906", "-2.892585", "E06000050", "Cheshire West and Chester", "30,637", "10"], "CH21EU": ["53.221579", "-2.884882", "E06000050", "Cheshire West and Chester", "27,465", "9"], "CH21EW": ["53.221075", "-2.890053", "E06000050", "Cheshire West and Chester", "30,637", "10"], "CH21EX": ["53.217564", "-2.885967", "E06000050", "Cheshire West and Chester", "27,465", "9"], "CH21EY": ["53.215017", "-2.901639", "E06000050", "Cheshire West and Chester", "30,637", "10"], "CH21EZ": ["53.214778", "-2.903775", "E06000050", "Cheshire West and Chester", "30,637", "10"], "CH21FA": ["53.213750", "-2.897104", "E06000050", "Cheshire West and Chester", "30,637", "10"], "CH21FB": ["53.213768", "-2.897179", "E06000050", "Cheshire West and Chester", "30,637", "10"], "CH21FD": ["53.212984", "-2.898317", "E06000050", "Cheshire West and Chester", "30,637", "10"], "CH21FE": ["53.225530", "-2.874867", "E06000050", "Cheshire West and Chester", "27,465", "9"], "CH21FF": ["53.206231", "-2.895002", "E06000050", "Cheshire West and Chester", "21,965", "7"], "CH21FG": ["53.196800", "-2.893952", "E06000050", "Cheshire West and Chester", "11,969", "4"], "CH21FH": ["53.196900", "-2.893835", "E06000050", "Cheshire West and Chester", "11,969", "4"], "CH21FJ": ["53.196900", "-2.893835", "E06000050", "Cheshire West and Chester", "11,969", "4"], "CH21FL": ["53.196520", "-2.894096", "E06000050", "Cheshire West and Chester", "11,969", "4"], "CH21HA": ["53.207017", "-2.877888", "E06000050", "Cheshire West and Chester", "29,069", "9"], "CH21HB": ["53.209985", "-2.881213", "E06000050", "Cheshire West and Chester", "22,227", "7"], "CH21HD": ["53.213783", "-2.884301", "E06000050", "Cheshire West and Chester", "22,227", "7"], "CH21HE": ["53.208425", "-2.881900", "E06000050", "Cheshire West and Chester", "29,069", "9"], "CH21HF": ["53.208703", "-2.880783", "E06000050", "Cheshire West and Chester", "29,069", "9"], "CH21HG": ["53.213892", "-2.886266", "E06000050", "Cheshire West and Chester", "21,965", "7"], "CH21HH": ["53.208116", "-2.881115", "E06000050", "Cheshire West and Chester", "29,069", "9"], "CH21HJ": ["53.211542", "-2.902300", "E06000050", "Cheshire West and Chester", "21,965", "7"], "CH21HL": ["53.197727", "-2.884480", "E06000050", "Cheshire West and Chester", "7,928", "3"], "CH21HN": ["53.220124", "-2.877692", "E06000050", "Cheshire West and Chester", "27,465", "9"], "CH21HP": ["53.212958", "-2.886441", "E06000050", "Cheshire West and Chester", "21,965", "7"], "CH21HQ": ["53.220055", "-2.876058", "E06000050", "Cheshire West and Chester", "27,465", "9"], "CH21HS": ["53.215794", "-2.887038", "E06000050", "Cheshire West and Chester", "27,465", "9"], "CH21HT": ["53.217363", "-2.883956", "E06000050", "Cheshire West and Chester", "27,465", "9"], "CH21HU": ["53.215545", "-2.885506", "E06000050", "Cheshire West and Chester", "22,227", "7"], "CH21HW": ["53.209770", "-2.879966", "E06000050", "Cheshire West and Chester", "29,069", "9"], "CH21HX": ["53.218778", "-2.882307", "E06000050", "Cheshire West and Chester", "22,227", "7"], "CH21HY": ["53.209210", "-2.879131", "E06000050", "Cheshire West and Chester", "29,069", "9"], "CH21HZ": ["53.219200", "-2.885956", "E06000050", "Cheshire West and Chester", "30,637", "10"], "CH21JA": ["53.219898", "-2.886464", "E06000050", "Cheshire West and Chester", "27,465", "9"], "CH21JB": ["53.219168", "-2.887917", "E06000050", "Cheshire West and Chester", "27,465", "9"], "CH21JD": ["53.219556", "-2.877935", "E06000050", "Cheshire West and Chester", "27,465", "9"], "CH21JE": ["53.219181", "-2.876400", "E06000050", "Cheshire West and Chester", "27,465", "9"], "CH21JF": ["53.218996", "-2.878283", "E06000050", "Cheshire West and Chester", "8,177", "3"], "CH21JG": ["53.217731", "-2.874274", "E06000050", "Cheshire West and Chester", "17,730", "6"], "CH21JH": ["53.211471", "-2.879731", "E06000050", "Cheshire West and Chester", "22,227", "7"], "CH21JJ": ["53.211129", "-2.879680", "E06000050", "Cheshire West and Chester", "22,227", "7"], "CH21JL": ["53.220783", "-2.878514", "E06000050", "Cheshire West and Chester", "27,465", "9"], "CH21JN": ["53.218247", "-2.876231", "E06000050", "Cheshire West and Chester", "8,177", "3"], "CH21JP": ["53.209576", "-2.874557", "E06000050", "Cheshire West and Chester", "29,069", "9"], "CH21JQ": ["53.218406", "-2.879065", "E06000050", "Cheshire West and Chester", "22,227", "7"], "CH21JR": ["53.208090", "-2.895489", "E06000050", "Cheshire West and Chester", "21,965", "7"], "CH21JT": ["53.221245", "-2.878135", "E06000050", "Cheshire West and Chester", "27,465", "9"], "CH21LA": ["53.219446", "-2.882726", "E06000050", "Cheshire West and Chester", "27,465", "9"], "CH21LB": ["53.219904", "-2.881926", "E06000050", "Cheshire West and Chester", "27,465", "9"], "CH21LD": ["53.220955", "-2.882937", "E06000050", "Cheshire West and Chester", "27,465", "9"], "CH21LE": ["53.222474", "-2.882084", "E06000050", "Cheshire West and Chester", "27,465", "9"], "CH21LF": ["53.219829", "-2.882434", "E06000050", "Cheshire West and Chester", "27,465", "9"], "CH21LG": ["53.223106", "-2.880554", "E06000050", "Cheshire West and Chester", "27,465", "9"], "CH21LH": ["53.227449", "-2.876315", "E06000050", "Cheshire West and Chester", "20,685", "7"], "CH21LJ": ["53.223652", "-2.875877", "E06000050", "Cheshire West and Chester", "27,465", "9"], "CH21LL": ["53.224748", "-2.874806", "E06000050", "Cheshire West and Chester", "27,465", "9"], "CH21LN": ["53.224957", "-2.875754", "E06000050", "Cheshire West and Chester", "27,465", "9"], "CH21LP": ["53.224199", "-2.877266", "E06000050", "Cheshire West and Chester", "27,465", "9"], "CH21LQ": ["53.223801", "-2.880104", "E06000050", "Cheshire West and Chester", "27,465", "9"], "CH21LR": ["53.221441", "-2.879591", "E06000050", "Cheshire West and Chester", "27,465", "9"], "CH21LS": ["53.221456", "-2.878678", "E06000050", "Cheshire West and Chester", "27,465", "9"], "CH21LT": ["53.221655", "-2.880974", "E06000050", "Cheshire West and Chester", "27,465", "9"], "CH21LU": ["53.219583", "-2.882863", "E06000050", "Cheshire West and Chester", "27,465", "9"], "CH21LW": ["53.223101", "-2.876285", "E06000050", "Cheshire West and Chester", "27,465", "9"], "CH21LX": ["53.220587", "-2.880832", "E06000050", "Cheshire West and Chester", "27,465", "9"], "CH21LY": ["53.224041", "-2.874387", "E06000050", "Cheshire West and Chester", "27,465", "9"], "CH21LZ": ["53.222569", "-2.877757", "E06000050", "Cheshire West and Chester", "27,465", "9"], "CH21NA": ["53.217420", "-2.874702", "E06000050", "Cheshire West and Chester", "17,730", "6"], "CH21NB": ["53.216435", "-2.872091", "E06000050", "Cheshire West and Chester", "17,730", "6"], "CH21ND": ["53.216238", "-2.875606", "E06000050", "Cheshire West and Chester", "17,730", "6"], "CH21NE": ["53.216278", "-2.876311", "E06000050", "Cheshire West and Chester", "17,730", "6"], "CH21NF": ["53.215966", "-2.873534", "E06000050", "Cheshire West and Chester", "17,730", "6"], "CH21NG": ["53.216646", "-2.871526", "E06000050", "Cheshire West and Chester", "17,730", "6"], "CH21NH": ["53.215125", "-2.871780", "E06000050", "Cheshire West and Chester", "17,730", "6"], "CH21NJ": ["53.215138", "-2.871241", "E06000050", "Cheshire West and Chester", "17,730", "6"], "CH21NL": ["53.212965", "-2.873323", "E06000050", "Cheshire West and Chester", "17,730", "6"], "CH21NN": ["53.213635", "-2.872663", "E06000050", "Cheshire West and Chester", "17,730", "6"], "CH21NP": ["53.215097", "-2.876856", "E06000050", "Cheshire West and Chester", "8,177", "3"], "CH21NQ": ["53.215092", "-2.872558", "E06000050", "Cheshire West and Chester", "17,730", "6"], "CH21NR": ["53.215250", "-2.875601", "E06000050", "Cheshire West and Chester", "8,177", "3"], "CH21NS": ["53.215529", "-2.876775", "E06000050", "Cheshire West and Chester", "8,177", "3"], "CH21NT": ["53.220372", "-2.881547", "E06000050", "Cheshire West and Chester", "27,465", "9"], "CH21NW": ["53.211638", "-2.872907", "E06000050", "Cheshire West and Chester", "17,730", "6"], "CH21PA": ["53.208322", "-2.877631", "E06000050", "Cheshire West and Chester", "29,069", "9"], "CH21PB": ["53.209026", "-2.878498", "E06000050", "Cheshire West and Chester", "29,069", "9"], "CH21PD": ["53.209222", "-2.877544", "E06000050", "Cheshire West and Chester", "29,069", "9"], "CH21PE": ["53.212690", "-2.870397", "E06000050", "Cheshire West and Chester", "17,730", "6"], "CH21PF": ["53.206960", "-2.876974", "E06000050", "Cheshire West and Chester", "29,069", "9"], "CH21PG": ["53.206794", "-2.876372", "E06000050", "Cheshire West and Chester", "29,069", "9"], "CH21PH": ["53.213225", "-2.871037", "E06000050", "Cheshire West and Chester", "17,730", "6"], "CH21PJ": ["53.209356", "-2.875166", "E06000050", "Cheshire West and Chester", "29,069", "9"], "CH21PL": ["53.210947", "-2.872683", "E06000050", "Cheshire West and Chester", "29,069", "9"], "CH21PN": ["53.210908", "-2.873131", "E06000050", "Cheshire West and Chester", "29,069", "9"], "CH21PP": ["53.211635", "-2.869642", "E06000050", "Cheshire West and Chester", "29,069", "9"], "CH21PQ": ["53.209161", "-2.874743", "E06000050", "Cheshire West and Chester", "29,069", "9"], "CH21PR": ["53.213174", "-2.868161", "E06000050", "Cheshire West and Chester", "17,730", "6"], "CH21PS": ["53.208166", "-2.871983", "E06000050", "Cheshire West and Chester", "5,984", "2"], "CH21PT": ["53.209007", "-2.871206", "E06000050", "Cheshire West and Chester", "5,984", "2"], "CH21PU": ["53.210464", "-2.871206", "E06000050", "Cheshire West and Chester", "5,984", "2"], "CH21PW": ["53.210390", "-2.872672", "E06000050", "Cheshire West and Chester", "29,069", "9"], "CH21PX": ["53.209452", "-2.871799", "E06000050", "Cheshire West and Chester", "5,984", "2"], "CH21PY": ["53.209372", "-2.872995", "E06000050", "Cheshire West and Chester", "5,984", "2"], "CH21PZ": ["53.209647", "-2.872267", "E06000050", "Cheshire West and Chester", "5,984", "2"], "CH21QA": ["53.209269", "-2.872319", "E06000050", "Cheshire West and Chester", "5,984", "2"], "CH21QB": ["53.211260", "-2.871746", "E06000050", "Cheshire West and Chester", "29,069", "9"], "CH21QD": ["53.209815", "-2.877541", "E06000050", "Cheshire West and Chester", "29,069", "9"], "CH21QE": ["53.213934", "-2.875978", "E06000050", "Cheshire West and Chester", "8,177", "3"], "CH21QF": ["53.209686", "-2.876790", "E06000050", "Cheshire West and Chester", "29,069", "9"], "CH21QH": ["53.216894", "-2.876862", "E06000050", "Cheshire West and Chester", "8,177", "3"], "CH21QJ": ["53.216333", "-2.877136", "E06000050", "Cheshire West and Chester", "8,177", "3"], "CH21QL": ["53.214260", "-2.880552", "E06000050", "Cheshire West and Chester", "22,227", "7"], "CH21QN": ["53.213032", "-2.881261", "E06000050", "Cheshire West and Chester", "22,227", "7"], "CH21QP": ["53.213524", "-2.881645", "E06000050", "Cheshire West and Chester", "22,227", "7"], "CH21QR": ["53.212812", "-2.879415", "E06000050", "Cheshire West and Chester", "22,227", "7"], "CH21QS": ["53.212851", "-2.880269", "E06000050", "Cheshire West and Chester", "22,227", "7"], "CH21QT": ["53.214843", "-2.883140", "E06000050", "Cheshire West and Chester", "22,227", "7"], "CH21QU": ["53.215134", "-2.882682", "E06000050", "Cheshire West and Chester", "22,227", "7"], "CH21QW": ["53.214991", "-2.880238", "E06000050", "Cheshire West and Chester", "22,227", "7"], "CH21QX": ["53.214435", "-2.883626", "E06000050", "Cheshire West and Chester", "22,227", "7"], "CH21QY": ["53.215552", "-2.880923", "E06000050", "Cheshire West and Chester", "22,227", "7"], "CH21QZ": ["53.214295", "-2.881901", "E06000050", "Cheshire West and Chester", "22,227", "7"], "CH21RA": ["53.216609", "-2.882622", "E06000050", "Cheshire West and Chester", "22,227", "7"], "CH21RB": ["53.216405", "-2.879773", "E06000050", "Cheshire West and Chester", "22,227", "7"], "CH21RD": ["53.216392", "-2.881585", "E06000050", "Cheshire West and Chester", "22,227", "7"], "CH21RE": ["53.216004", "-2.881741", "E06000050", "Cheshire West and Chester", "22,227", "7"], "CH21RF": ["53.217154", "-2.878186", "E06000050", "Cheshire West and Chester", "8,177", "3"], "CH21RG": ["53.217004", "-2.879036", "E06000050", "Cheshire West and Chester", "8,177", "3"], "CH21RH": ["53.218768", "-2.879926", "E06000050", "Cheshire West and Chester", "22,227", "7"], "CH21RJ": ["53.217897", "-2.879833", "E06000050", "Cheshire West and Chester", "22,227", "7"], "CH21RL": ["53.217911", "-2.881586", "E06000050", "Cheshire West and Chester", "22,227", "7"], "CH21RN": ["53.217380", "-2.880183", "E06000050", "Cheshire West and Chester", "8,177", "3"], "CH21RP": ["53.217534", "-2.882403", "E06000050", "Cheshire West and Chester", "22,227", "7"], "CH21RQ": ["53.218214", "-2.878312", "E06000050", "Cheshire West and Chester", "8,177", "3"], "CH21RR": ["53.218095", "-2.877023", "E06000050", "Cheshire West and Chester", "8,177", "3"], "CH21SA": ["53.210905", "-2.874719", "E06000050", "Cheshire West and Chester", "22,227", "7"], "CH21SB": ["53.211373", "-2.874638", "E06000050", "Cheshire West and Chester", "17,730", "6"], "CH21SD": ["53.211550", "-2.875106", "E06000050", "Cheshire West and Chester", "17,730", "6"], "CH21SE": ["53.212352", "-2.875991", "E06000050", "Cheshire West and Chester", "17,730", "6"], "CH21SF": ["53.212240", "-2.874102", "E06000050", "Cheshire West and Chester", "17,730", "6"], "CH21SG": ["53.213141", "-2.875079", "E06000050", "Cheshire West and Chester", "17,730", "6"], "CH21SH": ["53.212771", "-2.876479", "E06000050", "Cheshire West and Chester", "8,177", "3"], "CH21SJ": ["53.213635", "-2.875074", "E06000050", "Cheshire West and Chester", "17,730", "6"], "CH21SL": ["53.213354", "-2.876700", "E06000050", "Cheshire West and Chester", "8,177", "3"], "CH21SN": ["53.214181", "-2.874156", "E06000050", "Cheshire West and Chester", "17,730", "6"], "CH21SP": ["53.213726", "-2.876199", "E06000050", "Cheshire West and Chester", "8,177", "3"], "CH21SQ": ["53.212975", "-2.875704", "E06000050", "Cheshire West and Chester", "17,730", "6"], "CH21SR": ["53.213682", "-2.877231", "E06000050", "Cheshire West and Chester", "8,177", "3"], "CH21SS": ["53.214918", "-2.874291", "E06000050", "Cheshire West and Chester", "8,177", "3"], "CH21ST": ["53.214730", "-2.875291", "E06000050", "Cheshire West and Chester", "8,177", "3"], "CH21SU": ["53.215427", "-2.875904", "E06000050", "Cheshire West and Chester", "8,177", "3"], "CH21SW": ["53.213384", "-2.873811", "E06000050", "Cheshire West and Chester", "17,730", "6"], "CH21SX": ["53.214597", "-2.877564", "E06000050", "Cheshire West and Chester", "8,177", "3"], "CH21SY": ["53.214211", "-2.877452", "E06000050", "Cheshire West and Chester", "8,177", "3"], "CH21SZ": ["53.212034", "-2.876494", "E06000050", "Cheshire West and Chester", "8,177", "3"], "CH21TA": ["53.211949", "-2.877076", "E06000050", "Cheshire West and Chester", "22,227", "7"], "CH21TB": ["53.213393", "-2.878678", "E06000050", "Cheshire West and Chester", "22,227", "7"], "CH21TD": ["53.213249", "-2.877447", "E06000050", "Cheshire West and Chester", "8,177", "3"], "CH21TE": ["53.214387", "-2.878924", "E06000050", "Cheshire West and Chester", "22,227", "7"], "CH21TF": ["53.211722", "-2.877371", "E06000050", "Cheshire West and Chester", "8,177", "3"], "CH21TG": ["53.211157", "-2.877135", "E06000050", "Cheshire West and Chester", "22,227", "7"], "CH21TH": ["53.210719", "-2.874370", "E06000050", "Cheshire West and Chester", "29,069", "9"], "CH21TL": ["53.212511", "-2.877581", "E06000050", "Cheshire West and Chester", "8,177", "3"], "CH21TQ": ["53.210771", "-2.877067", "E06000050", "Cheshire West and Chester", "22,227", "7"], "CH21UA": ["53.206196", "-2.897530", "E06000050", "Cheshire West and Chester", "21,965", "7"], "CH21UB": ["53.206162", "-2.898533", "E06000050", "Cheshire West and Chester", "21,965", "7"], "CH21UD": ["53.205924", "-2.899007", "E06000050", "Cheshire West and Chester", "21,965", "7"], "CH21UE": ["53.206238", "-2.899148", "E06000050", "Cheshire West and Chester", "21,965", "7"], "CH21UF": ["53.206153", "-2.899655", "E06000050", "Cheshire West and Chester", "21,965", "7"], "CH21UG": ["53.206521", "-2.899768", "E06000050", "Cheshire West and Chester", "21,965", "7"], "CH21UL": ["53.208800", "-2.897884", "E06000050", "Cheshire West and Chester", "21,965", "7"], "CH21WA": ["53.197727", "-2.884480", "E06000050", "Cheshire West and Chester", "7,928", "3"], "CH21WB": ["53.197727", "-2.884480", "E06000050", "Cheshire West and Chester", "7,928", "3"], "CH21WD": ["53.197727", "-2.884480", "E06000050", "Cheshire West and Chester", "7,928", "3"], "CH21WE": ["53.197727", "-2.884480", "E06000050", "Cheshire West and Chester", "7,928", "3"], "CH21WF": ["53.197727", "-2.884480", "E06000050", "Cheshire West and Chester", "7,928", "3"], "CH21WG": ["53.197727", "-2.884480", "E06000050", "Cheshire West and Chester", "7,928", "3"], "CH21WH": ["53.197727", "-2.884480", "E06000050", "Cheshire West and Chester", "7,928", "3"], "CH21WJ": ["53.197727", "-2.884480", "E06000050", "Cheshire West and Chester", "7,928", "3"], "CH21WL": ["53.197771", "-2.884630", "E06000050", "Cheshire West and Chester", "7,928", "3"], "CH21WN": ["53.197727", "-2.884480", "E06000050", "Cheshire West and Chester", "7,928", "3"], "CH21WP": ["53.197727", "-2.884480", "E06000050", "Cheshire West and Chester", "7,928", "3"], "CH21WQ": ["53.197727", "-2.884480", "E06000050", "Cheshire West and Chester", "7,928", "3"], "CH21WR": ["53.197727", "-2.884480", "E06000050", "Cheshire West and Chester", "7,928", "3"], "CH21WS": ["53.211767", "-2.899009", "E06000050", "Cheshire West and Chester", "30,637", "10"], "CH21WT": ["53.214775", "-2.881387", "E06000050", "Cheshire West and Chester", "22,227", "7"], "CH21WU": ["53.197727", "-2.884480", "E06000050", "Cheshire West and Chester", "7,928", "3"], "CH21WW": ["53.197727", "-2.884480", "E06000050", "Cheshire West and Chester", "7,928", "3"], "CH21WX": ["53.197727", "-2.884480", "E06000050", "Cheshire West and Chester", "7,928", "3"], "CH21WY": ["53.197727", "-2.884480", "E06000050", "Cheshire West and Chester", "7,928", "3"], "CH21WZ": ["53.197727", "-2.884480", "E06000050", "Cheshire West and Chester", "7,928", "3"], "CH21XA": ["53.197727", "-2.884480", "E06000050", "Cheshire West and Chester", "7,928", "3"], "CH21XR": ["53.197727", "-2.884480", "E06000050", "Cheshire West and Chester", "7,928", "3"], "CH21YT": ["53.197727", "-2.884480", "E06000050", "Cheshire West and Chester", "7,928", "3"], "CH21YU": ["53.197727", "-2.884480", "E06000050", "Cheshire West and Chester", "7,928", "3"], "CH21ZB": ["53.197727", "-2.884480", "E06000050", "Cheshire West and Chester", "7,928", "3"], "CH21ZQ": ["53.197727", "-2.884480", "E06000050", "Cheshire West and Chester", "7,928", "3"], "CH21ZR": ["53.197727", "-2.884480", "E06000050", "Cheshire West and Chester", "7,928", "3"], "CH21ZU": ["53.197727", "-2.884480", "E06000050", "Cheshire West and Chester", "7,928", "3"], "CH22AA": ["53.203486", "-2.893282", "E06000050", "Cheshire West and Chester", "26,310", "9"], "CH22AB": ["53.199006", "-2.891332", "E06000050", "Cheshire West and Chester", "7,928", "3"], "CH22AD": ["53.203590", "-2.893823", "E06000050", "Cheshire West and Chester", "26,310", "9"], "CH22AE": ["53.199598", "-2.891554", "E06000050", "Cheshire West and Chester", "7,928", "3"], "CH22AF": ["53.206369", "-2.892488", "E06000050", "Cheshire West and Chester", "21,965", "7"], "CH22AG": ["53.206293", "-2.892981", "E06000050", "Cheshire West and Chester", "21,965", "7"], "CH22AH": ["53.204444", "-2.892598", "E06000050", "Cheshire West and Chester", "21,965", "7"], "CH22AJ": ["53.204003", "-2.892664", "E06000050", "Cheshire West and Chester", "26,310", "9"], "CH22AL": ["53.203365", "-2.892635", "E06000050", "Cheshire West and Chester", "26,310", "9"], "CH22AN": ["53.202228", "-2.890875", "E06000050", "Cheshire West and Chester", "26,310", "9"], "CH22AP": ["53.201165", "-2.889925", "E06000050", "Cheshire West and Chester", "26,310", "9"], "CH22AQ": ["53.205085", "-2.892237", "E06000050", "Cheshire West and Chester", "21,965", "7"], "CH22AR": ["53.202183", "-2.889602", "E06000050", "Cheshire West and Chester", "26,310", "9"], "CH22AS": ["53.202667", "-2.888683", "E06000050", "Cheshire West and Chester", "26,310", "9"], "CH22AT": ["53.200646", "-2.890812", "E06000050", "Cheshire West and Chester", "26,310", "9"], "CH22AU": ["53.195988", "-2.891015", "E06000050", "Cheshire West and Chester", "7,928", "3"], "CH22AW": ["53.202105", "-2.891413", "E06000050", "Cheshire West and Chester", "26,310", "9"], "CH22AX": ["53.198459", "-2.893343", "E06000050", "Cheshire West and Chester", "11,969", "4"], "CH22AY": ["53.195406", "-2.891931", "E06000050", "Cheshire West and Chester", "7,928", "3"], "CH22AZ": ["53.201797", "-2.888411", "E06000050", "Cheshire West and Chester", "26,310", "9"], "CH22BA": ["53.199785", "-2.894148", "E06000050", "Cheshire West and Chester", "11,969", "4"], "CH22BB": ["53.197193", "-2.893345", "E06000050", "Cheshire West and Chester", "11,969", "4"], "CH22BD": ["53.195445", "-2.892367", "E06000050", "Cheshire West and Chester", "7,928", "3"], "CH22BE": ["53.203712", "-2.889544", "E06000050", "Cheshire West and Chester", "26,310", "9"], "CH22BF": ["53.203048", "-2.889455", "E06000050", "Cheshire West and Chester", "26,310", "9"], "CH22BG": ["53.204288", "-2.890708", "E06000050", "Cheshire West and Chester", "26,310", "9"], "CH22BH": ["53.199105", "-2.892532", "E06000050", "Cheshire West and Chester", "7,928", "3"], "CH22BJ": ["53.197464", "-2.893231", "E06000050", "Cheshire West and Chester", "11,969", "4"], "CH22BL": ["53.202973", "-2.887372", "E06000050", "Cheshire West and Chester", "29,898", "10"], "CH22BN": ["53.203044", "-2.885128", "E06000050", "Cheshire West and Chester", "29,898", "10"], "CH22BP": ["53.203791", "-2.887419", "E06000050", "Cheshire West and Chester", "29,898", "10"], "CH22BQ": ["53.201030", "-2.892362", "E06000050", "Cheshire West and Chester", "26,310", "9"], "CH22BR": ["53.204468", "-2.887014", "E06000050", "Cheshire West and Chester", "29,898", "10"], "CH22BS": ["53.204863", "-2.888325", "E06000050", "Cheshire West and Chester", "29,898", "10"], "CH22BT": ["53.206330", "-2.889253", "E06000050", "Cheshire West and Chester", "26,055", "8"], "CH22BU": ["53.206299", "-2.888564", "E06000050", "Cheshire West and Chester", "26,055", "8"], "CH22BW": ["53.203938", "-2.887018", "E06000050", "Cheshire West and Chester", "29,898", "10"], "CH22BX": ["53.207503", "-2.888619", "E06000050", "Cheshire West and Chester", "26,055", "8"], "CH22BY": ["53.206939", "-2.889610", "E06000050", "Cheshire West and Chester", "26,055", "8"], "CH22BZ": ["53.207733", "-2.890316", "E06000050", "Cheshire West and Chester", "26,055", "8"], "CH22DA": ["53.207000", "-2.887396", "E06000050", "Cheshire West and Chester", "26,055", "8"], "CH22DB": ["53.206667", "-2.887404", "E06000050", "Cheshire West and Chester", "26,055", "8"], "CH22DD": ["53.207597", "-2.888097", "E06000050", "Cheshire West and Chester", "26,055", "8"], "CH22DE": ["53.207771", "-2.887741", "E06000050", "Cheshire West and Chester", "26,055", "8"], "CH22DF": ["53.207605", "-2.887004", "E06000050", "Cheshire West and Chester", "26,055", "8"], "CH22DG": ["53.206414", "-2.887310", "E06000050", "Cheshire West and Chester", "26,055", "8"], "CH22DH": ["53.206309", "-2.886004", "E06000050", "Cheshire West and Chester", "26,055", "8"], "CH22DJ": ["53.207237", "-2.884616", "E06000050", "Cheshire West and Chester", "26,055", "8"], "CH22DL": ["53.205692", "-2.885602", "E06000050", "Cheshire West and Chester", "29,898", "10"], "CH22DN": ["53.205444", "-2.885058", "E06000050", "Cheshire West and Chester", "29,898", "10"], "CH22DP": ["53.205444", "-2.883875", "E06000050", "Cheshire West and Chester", "26,055", "8"], "CH22DQ": ["53.206970", "-2.884206", "E06000050", "Cheshire West and Chester", "26,055", "8"], "CH22DR": ["53.207536", "-2.885415", "E06000050", "Cheshire West and Chester", "26,055", "8"], "CH22DS": ["53.200172", "-2.890548", "E06000050", "Cheshire West and Chester", "7,928", "3"], "CH22DT": ["53.199983", "-2.889376", "E06000050", "Cheshire West and Chester", "7,928", "3"], "CH22DU": ["53.200294", "-2.888664", "E06000050", "Cheshire West and Chester", "7,928", "3"], "CH22DW": ["53.205897", "-2.883450", "E06000050", "Cheshire West and Chester", "26,055", "8"], "CH22DX": ["53.199504", "-2.889681", "E06000050", "Cheshire West and Chester", "7,928", "3"], "CH22DY": ["53.204072", "-2.893069", "E06000050", "Cheshire West and Chester", "26,310", "9"], "CH22DZ": ["53.199218", "-2.889480", "E06000050", "Cheshire West and Chester", "7,928", "3"], "CH22EA": ["53.199549", "-2.888424", "E06000050", "Cheshire West and Chester", "7,928", "3"], "CH22EB": ["53.202184", "-2.884691", "E06000050", "Cheshire West and Chester", "29,898", "10"], "CH22ED": ["53.203036", "-2.882613", "E06000050", "Cheshire West and Chester", "29,898", "10"], "CH22EE": ["53.202585", "-2.882693", "E06000050", "Cheshire West and Chester", "29,898", "10"], "CH22EF": ["53.202711", "-2.881558", "E06000050", "Cheshire West and Chester", "29,898", "10"], "CH22EG": ["53.203277", "-2.880327", "E06000050", "Cheshire West and Chester", "29,898", "10"], "CH22EH": ["53.203528", "-2.884060", "E06000050", "Cheshire West and Chester", "29,898", "10"], "CH22EJ": ["53.203875", "-2.883319", "E06000050", "Cheshire West and Chester", "29,898", "10"], "CH22EL": ["53.204001", "-2.882169", "E06000050", "Cheshire West and Chester", "29,898", "10"], "CH22EN": ["53.205173", "-2.880486", "E06000050", "Cheshire West and Chester", "29,898", "10"], "CH22EP": ["53.204522", "-2.883332", "E06000050", "Cheshire West and Chester", "29,898", "10"], "CH22EQ": ["53.203470", "-2.884598", "E06000050", "Cheshire West and Chester", "29,898", "10"], "CH22ER": ["53.203893", "-2.885715", "E06000050", "Cheshire West and Chester", "29,898", "10"], "CH22ES": ["53.204805", "-2.882799", "E06000050", "Cheshire West and Chester", "29,898", "10"], "CH22ET": ["53.204335", "-2.885604", "E06000050", "Cheshire West and Chester", "29,898", "10"], "CH22EU": ["53.206054", "-2.880474", "E06000050", "Cheshire West and Chester", "29,898", "10"], "CH22EW": ["53.204087", "-2.881377", "E06000050", "Cheshire West and Chester", "29,898", "10"], "CH22EX": ["53.205429", "-2.882303", "E06000050", "Cheshire West and Chester", "29,898", "10"], "CH22EY": ["53.205699", "-2.882203", "E06000050", "Cheshire West and Chester", "29,898", "10"], "CH22EZ": ["53.202813", "-2.881096", "E06000050", "Cheshire West and Chester", "29,898", "10"], "CH22FA": ["53.201738", "-2.886673", "E06000050", "Cheshire West and Chester", "29,898", "10"], "CH22FB": ["53.201455", "-2.887221", "E06000050", "Cheshire West and Chester", "26,310", "9"], "CH22FD": ["53.195876", "-2.892854", "E06000050", "Cheshire West and Chester", "11,969", "4"], "CH22FE": ["53.198185", "-2.890522", "E06000050", "Cheshire West and Chester", "7,928", "3"], "CH22FF": ["53.209090", "-2.868498", "E06000050", "Cheshire West and Chester", "29,069", "9"], "CH22FG": ["53.197403", "-2.891480", "E06000050", "Cheshire West and Chester", "7,928", "3"], "CH22FH": ["53.209090", "-2.868498", "E06000050", "Cheshire West and Chester", "29,069", "9"], "CH22FJ": ["53.207284", "-2.866830", "E06000050", "Cheshire West and Chester", "5,984", "2"], "CH22HA": ["53.198783", "-2.889995", "E06000050", "Cheshire West and Chester", "7,928", "3"], "CH22HB": ["53.199668", "-2.890583", "E06000050", "Cheshire West and Chester", "7,928", "3"], "CH22HD": ["53.204041", "-2.875537", "E06000050", "Cheshire West and Chester", "5,984", "2"], "CH22HE": ["53.204755", "-2.875792", "E06000050", "Cheshire West and Chester", "5,984", "2"], "CH22HF": ["53.197750", "-2.892189", "E06000050", "Cheshire West and Chester", "7,928", "3"], "CH22HH": ["53.205524", "-2.877560", "E06000050", "Cheshire West and Chester", "29,069", "9"], "CH22HJ": ["53.206967", "-2.878546", "E06000050", "Cheshire West and Chester", "29,069", "9"], "CH22HL": ["53.207064", "-2.881213", "E06000050", "Cheshire West and Chester", "26,055", "8"], "CH22HN": ["53.207923", "-2.882938", "E06000050", "Cheshire West and Chester", "26,055", "8"], "CH22HP": ["53.209080", "-2.884489", "E06000050", "Cheshire West and Chester", "26,055", "8"], "CH22HR": ["53.208860", "-2.883945", "E06000050", "Cheshire West and Chester", "26,055", "8"], "CH22HS": ["53.209858", "-2.882648", "E06000050", "Cheshire West and Chester", "26,055", "8"], "CH22HT": ["53.209570", "-2.883960", "E06000050", "Cheshire West and Chester", "26,055", "8"], "CH22HU": ["53.209064", "-2.885522", "E06000050", "Cheshire West and Chester", "26,055", "8"], "CH22HW": ["53.208027", "-2.883479", "E06000050", "Cheshire West and Chester", "26,055", "8"], "CH22HX": ["53.208641", "-2.886696", "E06000050", "Cheshire West and Chester", "26,055", "8"], "CH22HY": ["53.207424", "-2.886042", "E06000050", "Cheshire West and Chester", "26,055", "8"], "CH22HZ": ["53.207492", "-2.886552", "E06000050", "Cheshire West and Chester", "26,055", "8"], "CH22JA": ["53.208043", "-2.887342", "E06000050", "Cheshire West and Chester", "26,055", "8"], "CH22JB": ["53.209821", "-2.888772", "E06000050", "Cheshire West and Chester", "21,965", "7"], "CH22JD": ["53.209912", "-2.887456", "E06000050", "Cheshire West and Chester", "21,965", "7"], "CH22JE": ["53.209388", "-2.889047", "E06000050", "Cheshire West and Chester", "21,965", "7"], "CH22JF": ["53.208823", "-2.890114", "E06000050", "Cheshire West and Chester", "21,965", "7"], "CH22JG": ["53.208596", "-2.887938", "E06000050", "Cheshire West and Chester", "26,055", "8"], "CH22JH": ["53.209582", "-2.887105", "E06000050", "Cheshire West and Chester", "21,965", "7"], "CH22JJ": ["53.210399", "-2.888424", "E06000050", "Cheshire West and Chester", "21,965", "7"], "CH22JL": ["53.199051", "-2.892636", "E06000050", "Cheshire West and Chester", "7,928", "3"], "CH22JN": ["53.198134", "-2.892572", "E06000050", "Cheshire West and Chester", "7,928", "3"], "CH22JQ": ["53.208147", "-2.889111", "E06000050", "Cheshire West and Chester", "26,055", "8"], "CH22JT": ["53.198698", "-2.891640", "E06000050", "Cheshire West and Chester", "7,928", "3"], "CH22LA": ["53.204415", "-2.879632", "E06000050", "Cheshire West and Chester", "29,898", "10"], "CH22LB": ["53.205684", "-2.875780", "E06000050", "Cheshire West and Chester", "29,069", "9"], "CH22LD": ["53.205569", "-2.874295", "E06000050", "Cheshire West and Chester", "5,984", "2"], "CH22LE": ["53.205465", "-2.874922", "E06000050", "Cheshire West and Chester", "5,984", "2"], "CH22LF": ["53.205140", "-2.875095", "E06000050", "Cheshire West and Chester", "5,984", "2"], "CH22LG": ["53.205540", "-2.872034", "E06000050", "Cheshire West and Chester", "5,984", "2"], "CH22LH": ["53.206487", "-2.872892", "E06000050", "Cheshire West and Chester", "5,984", "2"], "CH22LJ": ["53.208098", "-2.870214", "E06000050", "Cheshire West and Chester", "5,984", "2"], "CH22LL": ["53.207252", "-2.870317", "E06000050", "Cheshire West and Chester", "5,984", "2"], "CH22LN": ["53.208030", "-2.867159", "E06000050", "Cheshire West and Chester", "5,984", "2"], "CH22LP": ["53.206376", "-2.872036", "E06000050", "Cheshire West and Chester", "5,984", "2"], "CH22LQ": ["53.205940", "-2.872731", "E06000050", "Cheshire West and Chester", "5,984", "2"], "CH22LR": ["53.207067", "-2.873502", "E06000050", "Cheshire West and Chester", "5,984", "2"], "CH22LS": ["53.207156", "-2.868698", "E06000050", "Cheshire West and Chester", "5,984", "2"], "CH22LT": ["53.206069", "-2.868586", "E06000050", "Cheshire West and Chester", "5,984", "2"], "CH22LU": ["53.206713", "-2.866533", "E06000050", "Cheshire West and Chester", "5,984", "2"], "CH22LW": ["53.207652", "-2.867256", "E06000050", "Cheshire West and Chester", "5,984", "2"], "CH22LX": ["53.207358", "-2.865633", "E06000050", "Cheshire West and Chester", "5,984", "2"], "CH22LY": ["53.207225", "-2.867801", "E06000050", "Cheshire West and Chester", "5,984", "2"], "CH22LZ": ["53.207433", "-2.866443", "E06000050", "Cheshire West and Chester", "5,984", "2"], "CH22NA": ["53.207801", "-2.865297", "E06000050", "Cheshire West and Chester", "5,984", "2"], "CH22NB": ["53.208086", "-2.863222", "E06000050", "Cheshire West and Chester", "29,069", "9"], "CH22ND": ["53.207919", "-2.862635", "E06000050", "Cheshire West and Chester", "29,069", "9"], "CH22NE": ["53.205915", "-2.873614", "E06000050", "Cheshire West and Chester", "5,984", "2"], "CH22PA": ["53.208336", "-2.860981", "E06000050", "Cheshire West and Chester", "29,069", "9"], "CH22PB": ["53.210011", "-2.861793", "E06000050", "Cheshire West and Chester", "26,435", "9"], "CH22PD": ["53.210680", "-2.863693", "E06000050", "Cheshire West and Chester", "26,435", "9"], "CH22PE": ["53.216275", "-2.865603", "E06000050", "Cheshire West and Chester", "17,730", "6"], "CH22PF": ["53.210172", "-2.864372", "E06000050", "Cheshire West and Chester", "29,069", "9"], "CH22PG": ["53.211270", "-2.866610", "E06000050", "Cheshire West and Chester", "29,069", "9"], "CH22PH": ["53.209642", "-2.866832", "E06000050", "Cheshire West and Chester", "29,069", "9"], "CH22PJ": ["53.209199", "-2.865894", "E06000050", "Cheshire West and Chester", "29,069", "9"], "CH22PL": ["53.209169", "-2.865100", "E06000050", "Cheshire West and Chester", "29,069", "9"], "CH22PN": ["53.211088", "-2.866996", "E06000050", "Cheshire West and Chester", "29,069", "9"], "CH22PP": ["53.209463", "-2.867921", "E06000050", "Cheshire West and Chester", "29,069", "9"], "CH22PQ": ["53.209729", "-2.864632", "E06000050", "Cheshire West and Chester", "29,069", "9"], "CH22PR": ["53.210866", "-2.867860", "E06000050", "Cheshire West and Chester", "29,069", "9"], "CH22PS": ["53.211483", "-2.869459", "E06000050", "Cheshire West and Chester", "29,069", "9"], "CH22PT": ["53.210552", "-2.868976", "E06000050", "Cheshire West and Chester", "29,069", "9"], "CH22PU": ["53.211090", "-2.870335", "E06000050", "Cheshire West and Chester", "29,069", "9"], "CH22PW": ["53.210959", "-2.867397", "E06000050", "Cheshire West and Chester", "29,069", "9"], "CH22PX": ["53.210114", "-2.869881", "E06000050", "Cheshire West and Chester", "5,984", "2"], "CH22PY": ["53.209798", "-2.870099", "E06000050", "Cheshire West and Chester", "5,984", "2"], "CH22PZ": ["53.209157", "-2.870371", "E06000050", "Cheshire West and Chester", "5,984", "2"], "CH22QA": ["53.208253", "-2.869590", "E06000050", "Cheshire West and Chester", "5,984", "2"], "CH22QB": ["53.209245", "-2.869474", "E06000050", "Cheshire West and Chester", "5,984", "2"], "CH22QD": ["53.208751", "-2.870632", "E06000050", "Cheshire West and Chester", "5,984", "2"], "CH22QE": ["53.208498", "-2.870493", "E06000050", "Cheshire West and Chester", "5,984", "2"], "CH22QF": ["53.209604", "-2.863372", "E06000050", "Cheshire West and Chester", "29,069", "9"], "CH22QY": ["53.201282", "-2.887487", "E06000050", "Cheshire West and Chester", "26,310", "9"], "CH22RA": ["53.201867", "-2.892275", "E06000050", "Cheshire West and Chester", "26,310", "9"], "CH22RB": ["53.200895", "-2.893617", "E06000050", "Cheshire West and Chester", "26,310", "9"], "CH22RD": ["53.202227", "-2.893405", "E06000050", "Cheshire West and Chester", "26,310", "9"], "CH22RE": ["53.197727", "-2.884480", "E06000050", "Cheshire West and Chester", "7,928", "3"], "CH22RF": ["53.201427", "-2.892161", "E06000050", "Cheshire West and Chester", "26,310", "9"], "CH22RH": ["53.203063", "-2.892180", "E06000050", "Cheshire West and Chester", "26,310", "9"], "CH22WA": ["53.197727", "-2.884480", "E06000050", "Cheshire West and Chester", "7,928", "3"], "CH22WB": ["53.197727", "-2.884480", "E06000050", "Cheshire West and Chester", "7,928", "3"], "CH22WD": ["53.205432", "-2.881898", "E06000050", "Cheshire West and Chester", "29,898", "10"], "CH22WE": ["53.197727", "-2.884480", "E06000050", "Cheshire West and Chester", "7,928", "3"], "CH22WF": ["53.197771", "-2.884630", "E06000050", "Cheshire West and Chester", "7,928", "3"], "CH22WG": ["53.197727", "-2.884480", "E06000050", "Cheshire West and Chester", "7,928", "3"], "CH22WH": ["53.197727", "-2.884480", "E06000050", "Cheshire West and Chester", "7,928", "3"], "CH22WJ": ["53.197727", "-2.884480", "E06000050", "Cheshire West and Chester", "7,928", "3"], "CH22WL": ["53.197727", "-2.884480", "E06000050", "Cheshire West and Chester", "7,928", "3"], "CH22WN": ["53.197727", "-2.884480", "E06000050", "Cheshire West and Chester", "7,928", "3"], "CH22WP": ["53.197727", "-2.884480", "E06000050", "Cheshire West and Chester", "7,928", "3"], "CH22WQ": ["53.197727", "-2.884480", "E06000050", "Cheshire West and Chester", "7,928", "3"], "CH22WR": ["53.205432", "-2.881898", "E06000050", "Cheshire West and Chester", "29,898", "10"], "CH22WS": ["53.197727", "-2.884480", "E06000050", "Cheshire West and Chester", "7,928", "3"], "CH22WU": ["53.197727", "-2.884480", "E06000050", "Cheshire West and Chester", "7,928", "3"], "CH22WW": ["53.205441", "-2.881824", "E06000050", "Cheshire West and Chester", "29,898", "10"], "CH22XA": ["53.208586", "-2.869880", "E06000050", "Cheshire West and Chester", "5,984", "2"], "CH22XB": ["53.205717", "-2.881066", "E06000050", "Cheshire West and Chester", "29,898", "10"], "CH22YF": ["53.197771", "-2.884630", "E06000050", "Cheshire West and Chester", "7,928", "3"], "CH22YU": ["53.197771", "-2.884630", "E06000050", "Cheshire West and Chester", "7,928", "3"], "CH23AA": ["53.199458", "-2.880099", "E06000050", "Cheshire West and Chester", "24,745", "8"], "CH23AB": ["53.199983", "-2.880888", "E06000050", "Cheshire West and Chester", "24,745", "8"], "CH23AD": ["53.195740", "-2.874769", "E06000050", "Cheshire West and Chester", "12,604", "4"], "CH23AE": ["53.197109", "-2.878165", "E06000050", "Cheshire West and Chester", "12,604", "4"], "CH23AF": ["53.199392", "-2.880189", "E06000050", "Cheshire West and Chester", "24,745", "8"], "CH23AG": ["53.200132", "-2.880203", "E06000050", "Cheshire West and Chester", "24,745", "8"], "CH23AH": ["53.198162", "-2.879100", "E06000050", "Cheshire West and Chester", "12,604", "4"], "CH23AJ": ["53.197333", "-2.876927", "E06000050", "Cheshire West and Chester", "12,604", "4"], "CH23AL": ["53.196425", "-2.874528", "E06000050", "Cheshire West and Chester", "12,604", "4"], "CH23AN": ["53.196886", "-2.871709", "E06000050", "Cheshire West and Chester", "12,604", "4"], "CH23AP": ["53.196977", "-2.873703", "E06000050", "Cheshire West and Chester", "27,769", "9"], "CH23AQ": ["53.198750", "-2.877450", "E06000050", "Cheshire West and Chester", "12,604", "4"], "CH23AR": ["53.197498", "-2.874161", "E06000050", "Cheshire West and Chester", "27,769", "9"], "CH23AS": ["53.198426", "-2.873821", "E06000050", "Cheshire West and Chester", "27,769", "9"], "CH23AT": ["53.198694", "-2.875323", "E06000050", "Cheshire West and Chester", "12,604", "4"], "CH23AU": ["53.198763", "-2.874411", "E06000050", "Cheshire West and Chester", "27,769", "9"], "CH23AW": ["53.198553", "-2.873271", "E06000050", "Cheshire West and Chester", "27,769", "9"], "CH23AX": ["53.198967", "-2.874835", "E06000050", "Cheshire West and Chester", "12,604", "4"], "CH23AY": ["53.199210", "-2.874467", "E06000050", "Cheshire West and Chester", "27,769", "9"], "CH23AZ": ["53.199178", "-2.875438", "E06000050", "Cheshire West and Chester", "12,604", "4"], "CH23BA": ["53.200059", "-2.876668", "E06000050", "Cheshire West and Chester", "12,604", "4"], "CH23BB": ["53.199650", "-2.874804", "E06000050", "Cheshire West and Chester", "12,604", "4"], "CH23BD": ["53.199546", "-2.876360", "E06000050", "Cheshire West and Chester", "12,604", "4"], "CH23BE": ["53.198627", "-2.875756", "E06000050", "Cheshire West and Chester", "12,604", "4"], "CH23BF": ["53.196500", "-2.874126", "E06000050", "Cheshire West and Chester", "12,604", "4"], "CH23BG": ["53.197693", "-2.875677", "E06000050", "Cheshire West and Chester", "27,769", "9"], "CH23BH": ["53.197510", "-2.874910", "E06000050", "Cheshire West and Chester", "27,769", "9"], "CH23BJ": ["53.197566", "-2.874642", "E06000050", "Cheshire West and Chester", "27,769", "9"], "CH23BL": ["53.198275", "-2.875988", "E06000050", "Cheshire West and Chester", "27,769", "9"], "CH23BN": ["53.198317", "-2.875256", "E06000050", "Cheshire West and Chester", "12,604", "4"], "CH23BP": ["53.195429", "-2.873041", "E06000050", "Cheshire West and Chester", "12,604", "4"], "CH23BQ": ["53.197633", "-2.875317", "E06000050", "Cheshire West and Chester", "27,769", "9"], "CH23BR": ["53.198833", "-2.877152", "E06000050", "Cheshire West and Chester", "12,604", "4"], "CH23BS": ["53.198651", "-2.877105", "E06000050", "Cheshire West and Chester", "12,604", "4"], "CH23BT": ["53.198332", "-2.877980", "E06000050", "Cheshire West and Chester", "12,604", "4"], "CH23BU": ["53.198816", "-2.878170", "E06000050", "Cheshire West and Chester", "12,604", "4"], "CH23BW": ["53.197814", "-2.876338", "E06000050", "Cheshire West and Chester", "27,769", "9"], "CH23BX": ["53.198468", "-2.877863", "E06000050", "Cheshire West and Chester", "12,604", "4"], "CH23BY": ["53.198299", "-2.878878", "E06000050", "Cheshire West and Chester", "12,604", "4"], "CH23BZ": ["53.197532", "-2.876856", "E06000050", "Cheshire West and Chester", "12,604", "4"], "CH23DA": ["53.197721", "-2.876830", "E06000050", "Cheshire West and Chester", "27,769", "9"], "CH23DB": ["53.196773", "-2.874865", "E06000050", "Cheshire West and Chester", "27,769", "9"], "CH23DD": ["53.198124", "-2.865866", "E06000050", "Cheshire West and Chester", "27,769", "9"], "CH23DE": ["53.199093", "-2.875975", "E06000050", "Cheshire West and Chester", "12,604", "4"], "CH23DF": ["53.200663", "-2.861650", "E06000050", "Cheshire West and Chester", "22,074", "7"], "CH23DG": ["53.193386", "-2.875918", "E06000050", "Cheshire West and Chester", "10,818", "4"], "CH23DH": ["53.193599", "-2.874667", "E06000050", "Cheshire West and Chester", "10,818", "4"], "CH23DJ": ["53.199238", "-2.884436", "E06000050", "Cheshire West and Chester", "24,745", "8"], "CH23DL": ["53.197805", "-2.870215", "E06000050", "Cheshire West and Chester", "27,769", "9"], "CH23DN": ["53.198070", "-2.868395", "E06000050", "Cheshire West and Chester", "27,769", "9"], "CH23DP": ["53.192846", "-2.875922", "E06000050", "Cheshire West and Chester", "10,818", "4"], "CH23DQ": ["53.200151", "-2.875113", "E06000050", "Cheshire West and Chester", "12,604", "4"], "CH23DR": ["53.193167", "-2.875106", "E06000050", "Cheshire West and Chester", "10,818", "4"], "CH23DS": ["53.193074", "-2.874221", "E06000050", "Cheshire West and Chester", "15,061", "5"], "CH23DT": ["53.194276", "-2.873452", "E06000050", "Cheshire West and Chester", "15,061", "5"], "CH23DU": ["53.194347", "-2.872346", "E06000050", "Cheshire West and Chester", "15,061", "5"], "CH23DW": ["53.195629", "-2.869109", "E06000050", "Cheshire West and Chester", "27,769", "9"], "CH23DX": ["53.194223", "-2.872089", "E06000050", "Cheshire West and Chester", "15,061", "5"], "CH23DY": ["53.194576", "-2.872979", "E06000050", "Cheshire West and Chester", "10,818", "4"], "CH23DZ": ["53.194634", "-2.872352", "E06000050", "Cheshire West and Chester", "15,061", "5"], "CH23EA": ["53.194383", "-2.871089", "E06000050", "Cheshire West and Chester", "15,061", "5"], "CH23EB": ["53.193988", "-2.872189", "E06000050", "Cheshire West and Chester", "12,312", "4"], "CH23ED": ["53.194319", "-2.870010", "E06000050", "Cheshire West and Chester", "15,061", "5"], "CH23EE": ["53.195281", "-2.870015", "E06000050", "Cheshire West and Chester", "12,604", "4"], "CH23EF": ["53.198682", "-2.864620", "E06000050", "Cheshire West and Chester", "22,074", "7"], "CH23EG": ["53.198335", "-2.866529", "E06000050", "Cheshire West and Chester", "27,769", "9"], "CH23EH": ["53.201840", "-2.855551", "E06000050", "Cheshire West and Chester", "22,074", "7"], "CH23EJ": ["53.198694", "-2.862958", "E06000050", "Cheshire West and Chester", "22,074", "7"], "CH23EL": ["53.199279", "-2.861653", "E06000050", "Cheshire West and Chester", "22,074", "7"], "CH23EN": ["53.200211", "-2.860743", "E06000050", "Cheshire West and Chester", "22,074", "7"], "CH23EP": ["53.201110", "-2.859474", "E06000050", "Cheshire West and Chester", "22,074", "7"], "CH23EQ": ["53.199743", "-2.863279", "E06000050", "Cheshire West and Chester", "22,074", "7"], "CH23ER": ["53.202307", "-2.856803", "E06000050", "Cheshire West and Chester", "22,074", "7"], "CH23ES": ["53.201995", "-2.856452", "E06000050", "Cheshire West and Chester", "22,074", "7"], "CH23ET": ["53.202927", "-2.858163", "E06000050", "Cheshire West and Chester", "8,086", "3"], "CH23EU": ["53.203797", "-2.857147", "E06000050", "Cheshire West and Chester", "8,086", "3"], "CH23EW": ["53.201002", "-2.857031", "E06000050", "Cheshire West and Chester", "22,074", "7"], "CH23EX": ["53.203162", "-2.856655", "E06000050", "Cheshire West and Chester", "22,074", "7"], "CH23EY": ["53.203492", "-2.858279", "E06000050", "Cheshire West and Chester", "8,086", "3"], "CH23EZ": ["53.205957", "-2.857984", "E06000050", "Cheshire West and Chester", "8,086", "3"], "CH23FA": ["53.197882", "-2.864589", "E06000050", "Cheshire West and Chester", "27,769", "9"], "CH23FB": ["53.199995", "-2.859541", "E06000050", "Cheshire West and Chester", "22,074", "7"], "CH23FD": ["53.198258", "-2.863638", "E06000050", "Cheshire West and Chester", "22,074", "7"], "CH23FE": ["53.198317", "-2.880061", "E06000050", "Cheshire West and Chester", "12,604", "4"], "CH23FF": ["53.193194", "-2.875046", "E06000050", "Cheshire West and Chester", "10,818", "4"], "CH23GA": ["53.196650", "-2.869668", "E06000050", "Cheshire West and Chester", "27,769", "9"], "CH23HA": ["53.195941", "-2.868232", "E06000050", "Cheshire West and Chester", "27,769", "9"], "CH23HB": ["53.197318", "-2.866808", "E06000050", "Cheshire West and Chester", "27,769", "9"], "CH23HD": ["53.195992", "-2.871122", "E06000050", "Cheshire West and Chester", "12,604", "4"], "CH23HE": ["53.195992", "-2.871122", "E06000050", "Cheshire West and Chester", "12,604", "4"], "CH23HF": ["53.198655", "-2.875667", "E06000050", "Cheshire West and Chester", "12,604", "4"], "CH23HG": ["53.201664", "-2.868707", "E06000050", "Cheshire West and Chester", "22,074", "7"], "CH23HH": ["53.199803", "-2.867412", "E06000050", "Cheshire West and Chester", "22,074", "7"], "CH23HJ": ["53.199992", "-2.868643", "E06000050", "Cheshire West and Chester", "27,769", "9"], "CH23HL": ["53.201276", "-2.867561", "E06000050", "Cheshire West and Chester", "22,074", "7"], "CH23HN": ["53.200394", "-2.869025", "E06000050", "Cheshire West and Chester", "27,769", "9"], "CH23HP": ["53.198704", "-2.867734", "E06000050", "Cheshire West and Chester", "27,769", "9"], "CH23HQ": ["53.199817", "-2.866708", "E06000050", "Cheshire West and Chester", "22,074", "7"], "CH23HR": ["53.198588", "-2.868556", "E06000050", "Cheshire West and Chester", "27,769", "9"], "CH23HS": ["53.199254", "-2.869975", "E06000050", "Cheshire West and Chester", "27,769", "9"], "CH23HT": ["53.199073", "-2.870226", "E06000050", "Cheshire West and Chester", "27,769", "9"], "CH23HU": ["53.199315", "-2.867806", "E06000050", "Cheshire West and Chester", "27,769", "9"], "CH23HW": ["53.199383", "-2.869529", "E06000050", "Cheshire West and Chester", "27,769", "9"], "CH23HX": ["53.199732", "-2.870973", "E06000050", "Cheshire West and Chester", "27,769", "9"], "CH23HY": ["53.199460", "-2.872539", "E06000050", "Cheshire West and Chester", "27,769", "9"], "CH23HZ": ["53.200228", "-2.872031", "E06000050", "Cheshire West and Chester", "12,604", "4"], "CH23JA": ["53.199151", "-2.871725", "E06000050", "Cheshire West and Chester", "27,769", "9"], "CH23JB": ["53.199166", "-2.870992", "E06000050", "Cheshire West and Chester", "27,769", "9"], "CH23JD": ["53.198732", "-2.871312", "E06000050", "Cheshire West and Chester", "27,769", "9"], "CH23JE": ["53.199093", "-2.872382", "E06000050", "Cheshire West and Chester", "27,769", "9"], "CH23JF": ["53.199977", "-2.873194", "E06000050", "Cheshire West and Chester", "12,604", "4"], "CH23JG": ["53.199924", "-2.874211", "E06000050", "Cheshire West and Chester", "12,604", "4"], "CH23JH": ["53.200675", "-2.873522", "E06000050", "Cheshire West and Chester", "12,604", "4"], "CH23JJ": ["53.200989", "-2.873663", "E06000050", "Cheshire West and Chester", "12,604", "4"], "CH23JL": ["53.204458", "-2.858927", "E06000050", "Cheshire West and Chester", "8,086", "3"], "CH23JN": ["53.200394", "-2.872723", "E06000050", "Cheshire West and Chester", "12,604", "4"], "CH23JP": ["53.203891", "-2.863976", "E06000050", "Cheshire West and Chester", "8,086", "3"], "CH23JQ": ["53.199068", "-2.873370", "E06000050", "Cheshire West and Chester", "27,769", "9"], "CH23JR": ["53.202816", "-2.864733", "E06000050", "Cheshire West and Chester", "22,074", "7"], "CH23JS": ["53.202795", "-2.865211", "E06000050", "Cheshire West and Chester", "22,074", "7"], "CH23JT": ["53.201377", "-2.864794", "E06000050", "Cheshire West and Chester", "22,074", "7"], "CH23JU": ["53.201982", "-2.863264", "E06000050", "Cheshire West and Chester", "8,086", "3"], "CH23JW": ["53.204244", "-2.864881", "E06000050", "Cheshire West and Chester", "31,428", "10"], "CH23JX": ["53.203205", "-2.863228", "E06000050", "Cheshire West and Chester", "8,086", "3"], "CH23JY": ["53.203613", "-2.862698", "E06000050", "Cheshire West and Chester", "8,086", "3"], "CH23JZ": ["53.204961", "-2.862695", "E06000050", "Cheshire West and Chester", "8,086", "3"], "CH23LA": ["53.204998", "-2.860135", "E06000050", "Cheshire West and Chester", "8,086", "3"], "CH23LB": ["53.204594", "-2.859978", "E06000050", "Cheshire West and Chester", "8,086", "3"], "CH23LD": ["53.205522", "-2.861029", "E06000050", "Cheshire West and Chester", "8,086", "3"], "CH23LE": ["53.202568", "-2.861793", "E06000050", "Cheshire West and Chester", "8,086", "3"], "CH23LF": ["53.202625", "-2.861330", "E06000050", "Cheshire West and Chester", "8,086", "3"], "CH23LG": ["53.201888", "-2.858816", "E06000050", "Cheshire West and Chester", "22,074", "7"], "CH23LH": ["53.204214", "-2.860314", "E06000050", "Cheshire West and Chester", "8,086", "3"], "CH23LJ": ["53.202352", "-2.860606", "E06000050", "Cheshire West and Chester", "22,074", "7"], "CH23LL": ["53.202454", "-2.860084", "E06000050", "Cheshire West and Chester", "8,086", "3"], "CH23LN": ["53.203972", "-2.859951", "E06000050", "Cheshire West and Chester", "8,086", "3"], "CH23LP": ["53.205546", "-2.858844", "E06000050", "Cheshire West and Chester", "8,086", "3"], "CH23LQ": ["53.202891", "-2.859360", "E06000050", "Cheshire West and Chester", "8,086", "3"], "CH23LR": ["53.205725", "-2.860195", "E06000050", "Cheshire West and Chester", "8,086", "3"], "CH23LS": ["53.204557", "-2.857671", "E06000050", "Cheshire West and Chester", "8,086", "3"], "CH23LT": ["53.205457", "-2.862510", "E06000050", "Cheshire West and Chester", "8,086", "3"], "CH23LU": ["53.206109", "-2.861790", "E06000050", "Cheshire West and Chester", "31,428", "10"], "CH23LW": ["53.203785", "-2.859633", "E06000050", "Cheshire West and Chester", "8,086", "3"], "CH23LX": ["53.205688", "-2.861706", "E06000050", "Cheshire West and Chester", "8,086", "3"], "CH23LY": ["53.205199", "-2.860873", "E06000050", "Cheshire West and Chester", "8,086", "3"], "CH23LZ": ["53.192751", "-2.874154", "E06000050", "Cheshire West and Chester", "12,312", "4"], "CH23NA": ["53.201326", "-2.871829", "E06000050", "Cheshire West and Chester", "12,604", "4"], "CH23NB": ["53.201464", "-2.871412", "E06000050", "Cheshire West and Chester", "12,604", "4"], "CH23ND": ["53.201684", "-2.870848", "E06000050", "Cheshire West and Chester", "27,769", "9"], "CH23NE": ["53.197853", "-2.879632", "E06000050", "Cheshire West and Chester", "12,604", "4"], "CH23NF": ["53.199600", "-2.878036", "E06000050", "Cheshire West and Chester", "12,604", "4"], "CH23NG": ["53.201326", "-2.871829", "E06000050", "Cheshire West and Chester", "12,604", "4"], "CH23NH": ["53.199344", "-2.878495", "E06000050", "Cheshire West and Chester", "12,604", "4"], "CH23NJ": ["53.200583", "-2.875152", "E06000050", "Cheshire West and Chester", "12,604", "4"], "CH23NL": ["53.201924", "-2.872380", "E06000050", "Cheshire West and Chester", "31,428", "10"], "CH23NN": ["53.201346", "-2.870317", "E06000050", "Cheshire West and Chester", "27,769", "9"], "CH23NP": ["53.199472", "-2.877031", "E06000050", "Cheshire West and Chester", "12,604", "4"], "CH23NQ": ["53.198176", "-2.880523", "E06000050", "Cheshire West and Chester", "12,604", "4"], "CH23NR": ["53.200002", "-2.875919", "E06000050", "Cheshire West and Chester", "12,604", "4"], "CH23NS": ["53.203336", "-2.871076", "E06000050", "Cheshire West and Chester", "31,428", "10"], "CH23NT": ["53.203948", "-2.867331", "E06000050", "Cheshire West and Chester", "31,428", "10"], "CH23NU": ["53.205944", "-2.863598", "E06000050", "Cheshire West and Chester", "31,428", "10"], "CH23NW": ["53.204464", "-2.864332", "E06000050", "Cheshire West and Chester", "31,428", "10"], "CH23NX": ["53.206910", "-2.860533", "E06000050", "Cheshire West and Chester", "31,428", "10"], "CH23NY": ["53.207129", "-2.861241", "E06000050", "Cheshire West and Chester", "31,428", "10"], "CH23NZ": ["53.208170", "-2.856486", "E06000050", "Cheshire West and Chester", "26,435", "9"], "CH23PA": ["53.208100", "-2.855032", "E06000050", "Cheshire West and Chester", "26,435", "9"], "CH23PB": ["53.203636", "-2.868208", "E06000050", "Cheshire West and Chester", "31,428", "10"], "CH23PD": ["53.206233", "-2.854680", "E06000050", "Cheshire West and Chester", "26,435", "9"], "CH23PE": ["53.198934", "-2.876870", "E06000050", "Cheshire West and Chester", "12,604", "4"], "CH23PF": ["53.195949", "-2.870777", "E06000050", "Cheshire West and Chester", "12,604", "4"], "CH23PG": ["53.195885", "-2.869728", "E06000050", "Cheshire West and Chester", "12,604", "4"], "CH23PH": ["53.199966", "-2.883223", "E06000050", "Cheshire West and Chester", "24,745", "8"], "CH23PJ": ["53.195338", "-2.870824", "E06000050", "Cheshire West and Chester", "12,604", "4"], "CH23PL": ["53.199741", "-2.882006", "E06000050", "Cheshire West and Chester", "24,745", "8"], "CH23PN": ["53.199711", "-2.882350", "E06000050", "Cheshire West and Chester", "24,745", "8"], "CH23PP": ["53.201124", "-2.883352", "E06000050", "Cheshire West and Chester", "24,745", "8"], "CH23PQ": ["53.199276", "-2.877970", "E06000050", "Cheshire West and Chester", "12,604", "4"], "CH23PR": ["53.198781", "-2.881777", "E06000050", "Cheshire West and Chester", "24,745", "8"], "CH23PS": ["53.199708", "-2.882769", "E06000050", "Cheshire West and Chester", "24,745", "8"], "CH23PT": ["53.200987", "-2.883664", "E06000050", "Cheshire West and Chester", "24,745", "8"], "CH23PU": ["53.200699", "-2.883762", "E06000050", "Cheshire West and Chester", "24,745", "8"], "CH23PW": ["53.201486", "-2.883135", "E06000050", "Cheshire West and Chester", "29,898", "10"], "CH23PX": ["53.200848", "-2.884260", "E06000050", "Cheshire West and Chester", "24,745", "8"], "CH23PY": ["53.201433", "-2.884182", "E06000050", "Cheshire West and Chester", "24,745", "8"], "CH23PZ": ["53.203676", "-2.866397", "E06000050", "Cheshire West and Chester", "31,428", "10"], "CH23QA": ["53.200374", "-2.883861", "E06000050", "Cheshire West and Chester", "24,745", "8"], "CH23QB": ["53.200700", "-2.882445", "E06000050", "Cheshire West and Chester", "24,745", "8"], "CH23QD": ["53.200004", "-2.881742", "E06000050", "Cheshire West and Chester", "24,745", "8"], "CH23QE": ["53.200419", "-2.881526", "E06000050", "Cheshire West and Chester", "24,745", "8"], "CH23QF": ["53.200946", "-2.880684", "E06000050", "Cheshire West and Chester", "24,745", "8"], "CH23QG": ["53.201103", "-2.881346", "E06000050", "Cheshire West and Chester", "24,745", "8"], "CH23QH": ["53.201925", "-2.880868", "E06000050", "Cheshire West and Chester", "29,898", "10"], "CH23QJ": ["53.202891", "-2.877789", "E06000050", "Cheshire West and Chester", "24,745", "8"], "CH23QL": ["53.202162", "-2.877954", "E06000050", "Cheshire West and Chester", "24,745", "8"], "CH23QN": ["53.201033", "-2.879922", "E06000050", "Cheshire West and Chester", "24,745", "8"], "CH23QP": ["53.201484", "-2.879647", "E06000050", "Cheshire West and Chester", "24,745", "8"], "CH23QQ": ["53.202156", "-2.881172", "E06000050", "Cheshire West and Chester", "29,898", "10"], "CH23QR": ["53.201490", "-2.878928", "E06000050", "Cheshire West and Chester", "24,745", "8"], "CH23QS": ["53.201723", "-2.876508", "E06000050", "Cheshire West and Chester", "24,745", "8"], "CH23QT": ["53.200957", "-2.876747", "E06000050", "Cheshire West and Chester", "24,745", "8"], "CH23QU": ["53.200506", "-2.878219", "E06000050", "Cheshire West and Chester", "24,745", "8"], "CH23QW": ["53.200770", "-2.878600", "E06000050", "Cheshire West and Chester", "24,745", "8"], "CH23QX": ["53.199089", "-2.882651", "E06000050", "Cheshire West and Chester", "24,745", "8"], "CH23QY": ["53.202882", "-2.870543", "E06000050", "Cheshire West and Chester", "31,428", "10"], "CH23QZ": ["53.209528", "-2.863910", "E06000050", "Cheshire West and Chester", "29,069", "9"], "CH23RB": ["53.201657", "-2.874470", "E06000050", "Cheshire West and Chester", "31,428", "10"], "CH23RD": ["53.202665", "-2.873099", "E06000050", "Cheshire West and Chester", "31,428", "10"], "CH23RE": ["53.203589", "-2.872114", "E06000050", "Cheshire West and Chester", "31,428", "10"], "CH23RF": ["53.203089", "-2.874125", "E06000050", "Cheshire West and Chester", "31,428", "10"], "CH23RG": ["53.204396", "-2.871172", "E06000050", "Cheshire West and Chester", "31,428", "10"], "CH23RH": ["53.203573", "-2.874270", "E06000050", "Cheshire West and Chester", "31,428", "10"], "CH23RJ": ["53.203341", "-2.874085", "E06000050", "Cheshire West and Chester", "31,428", "10"], "CH23RL": ["53.203940", "-2.869636", "E06000050", "Cheshire West and Chester", "31,428", "10"], "CH23RN": ["53.204507", "-2.868300", "E06000050", "Cheshire West and Chester", "31,428", "10"], "CH23RP": ["53.205277", "-2.866309", "E06000050", "Cheshire West and Chester", "31,428", "10"], "CH23RQ": ["53.202812", "-2.875168", "E06000050", "Cheshire West and Chester", "31,428", "10"], "CH23RR": ["53.205625", "-2.866661", "E06000050", "Cheshire West and Chester", "31,428", "10"], "CH23RS": ["53.205976", "-2.866593", "E06000050", "Cheshire West and Chester", "31,428", "10"], "CH23RT": ["53.206222", "-2.863678", "E06000050", "Cheshire West and Chester", "31,428", "10"], "CH23RU": ["53.208233", "-2.863973", "E06000050", "Cheshire West and Chester", "29,069", "9"], "CH23RW": ["53.205100", "-2.865932", "E06000050", "Cheshire West and Chester", "31,428", "10"], "CH23RX": ["53.208989", "-2.863899", "E06000050", "Cheshire West and Chester", "29,069", "9"], "CH23RY": ["53.208443", "-2.864771", "E06000050", "Cheshire West and Chester", "29,069", "9"], "CH23RZ": ["53.201351", "-2.875722", "E06000050", "Cheshire West and Chester", "24,745", "8"], "CH23SA": ["53.207363", "-2.862459", "E06000050", "Cheshire West and Chester", "31,428", "10"], "CH23SB": ["53.203870", "-2.869052", "E06000050", "Cheshire West and Chester", "31,428", "10"], "CH23SD": ["53.194568", "-2.875209", "E06000050", "Cheshire West and Chester", "10,818", "4"], "CH23SE": ["53.194962", "-2.876654", "E06000050", "Cheshire West and Chester", "10,818", "4"], "CH23SF": ["53.198677", "-2.872673", "E06000050", "Cheshire West and Chester", "27,769", "9"], "CH23SG": ["53.202283", "-2.871249", "E06000050", "Cheshire West and Chester", "31,428", "10"], "CH23SL": ["53.203093", "-2.869933", "E06000050", "Cheshire West and Chester", "31,428", "10"], "CH23TA": ["53.198418", "-2.869943", "E06000050", "Cheshire West and Chester", "27,769", "9"], "CH23TB": ["53.196856", "-2.869762", "E06000050", "Cheshire West and Chester", "27,769", "9"], "CH23WA": ["53.197727", "-2.884480", "E06000050", "Cheshire West and Chester", "7,928", "3"], "CH23WB": ["53.197727", "-2.884480", "E06000050", "Cheshire West and Chester", "7,928", "3"], "CH23WD": ["53.197727", "-2.884480", "E06000050", "Cheshire West and Chester", "7,928", "3"], "CH23WE": ["53.197727", "-2.884480", "E06000050", "Cheshire West and Chester", "7,928", "3"], "CH23WF": ["53.197727", "-2.884480", "E06000050", "Cheshire West and Chester", "7,928", "3"], "CH23WG": ["53.199953", "-2.870229", "E06000050", "Cheshire West and Chester", "27,769", "9"], "CH23WH": ["53.197727", "-2.884480", "E06000050", "Cheshire West and Chester", "7,928", "3"], "CH23WJ": ["53.197727", "-2.884480", "E06000050", "Cheshire West and Chester", "7,928", "3"], "CH23WL": ["53.199907", "-2.870393", "E06000050", "Cheshire West and Chester", "27,769", "9"], "CH23WN": ["53.197727", "-2.884480", "E06000050", "Cheshire West and Chester", "7,928", "3"], "CH23WP": ["53.197727", "-2.884480", "E06000050", "Cheshire West and Chester", "7,928", "3"], "CH23WQ": ["53.197727", "-2.884480", "E06000050", "Cheshire West and Chester", "7,928", "3"], "CH23WR": ["53.197727", "-2.884480", "E06000050", "Cheshire West and Chester", "7,928", "3"], "CH23WS": ["53.197727", "-2.884480", "E06000050", "Cheshire West and Chester", "7,928", "3"], "CH23WT": ["53.197727", "-2.884480", "E06000050", "Cheshire West and Chester", "7,928", "3"], "CH23WU": ["53.197727", "-2.884480", "E06000050", "Cheshire West and Chester", "7,928", "3"], "CH23WW": ["53.197727", "-2.884480", "E06000050", "Cheshire West and Chester", "7,928", "3"], "CH23WX": ["53.197727", "-2.884480", "E06000050", "Cheshire West and Chester", "7,928", "3"], "CH23WY": ["53.197727", "-2.884480", "E06000050", "Cheshire West and Chester", "7,928", "3"], "CH23WZ": ["53.197727", "-2.884480", "E06000050", "Cheshire West and Chester", "7,928", "3"], "CH23XA": ["53.197727", "-2.884480", "E06000050", "Cheshire West and Chester", "7,928", "3"], "CH23XB": ["53.197727", "-2.884480", "E06000050", "Cheshire West and Chester", "7,928", "3"], "CH23XD": ["53.199907", "-2.870393", "E06000050", "Cheshire West and Chester", "27,769", "9"], "CH23XE": ["53.199907", "-2.870393", "E06000050", "Cheshire West and Chester", "27,769", "9"], "CH23XF": ["53.199907", "-2.870393", "E06000050", "Cheshire West and Chester", "27,769", "9"], "CH23XG": ["53.197727", "-2.884480", "E06000050", "Cheshire West and Chester", "7,928", "3"], "CH23XH": ["53.202283", "-2.871249", "E06000050", "Cheshire West and Chester", "31,428", "10"], "CH23XJ": ["53.197727", "-2.884480", "E06000050", "Cheshire West and Chester", "7,928", "3"], "CH23XL": ["53.197727", "-2.884480", "E06000050", "Cheshire West and Chester", "7,928", "3"], "CH23XN": ["53.197727", "-2.884480", "E06000050", "Cheshire West and Chester", "7,928", "3"], "CH23XP": ["53.197727", "-2.884480", "E06000050", "Cheshire West and Chester", "7,928", "3"], "CH23XR": ["53.197727", "-2.884480", "E06000050", "Cheshire West and Chester", "7,928", "3"], "CH23XS": ["53.197727", "-2.884480", "E06000050", "Cheshire West and Chester", "7,928", "3"], "CH23YA": ["53.197727", "-2.884480", "E06000050", "Cheshire West and Chester", "7,928", "3"], "CH23YB": ["53.197727", "-2.884480", "E06000050", "Cheshire West and Chester", "7,928", "3"], "CH23YG": ["53.197727", "-2.884480", "E06000050", "Cheshire West and Chester", "7,928", "3"], "CH23YP": ["53.197727", "-2.884480", "E06000050", "Cheshire West and Chester", "7,928", "3"], "CH23YQ": ["53.197727", "-2.884480", "E06000050", "Cheshire West and Chester", "7,928", "3"], "CH23YR": ["53.197727", "-2.884480", "E06000050", "Cheshire West and Chester", "7,928", "3"], "CH23YS": ["53.197727", "-2.884480", "E06000050", "Cheshire West and Chester", "7,928", "3"], "CH23YY": ["53.197727", "-2.884480", "E06000050", "Cheshire West and Chester", "7,928", "3"], "CH23ZA": ["53.200110", "-2.869783", "E06000050", "Cheshire West and Chester", "27,769", "9"], "CH23ZB": ["53.197727", "-2.884480", "E06000050", "Cheshire West and Chester", "7,928", "3"], "CH23ZD": ["53.197727", "-2.884480", "E06000050", "Cheshire West and Chester", "7,928", "3"], "CH23ZE": ["53.199981", "-2.870140", "E06000050", "Cheshire West and Chester", "27,769", "9"], "CH23ZF": ["53.197727", "-2.884480", "E06000050", "Cheshire West and Chester", "7,928", "3"], "CH23ZG": ["53.199953", "-2.870229", "E06000050", "Cheshire West and Chester", "27,769", "9"], "CH23ZH": ["53.197727", "-2.884480", "E06000050", "Cheshire West and Chester", "7,928", "3"], "CH23ZJ": ["53.197727", "-2.884480", "E06000050", "Cheshire West and Chester", "7,928", "3"], "CH23ZL": ["53.197727", "-2.884480", "E06000050", "Cheshire West and Chester", "7,928", "3"], "CH23ZN": ["53.200110", "-2.869783", "E06000050", "Cheshire West and Chester", "27,769", "9"], "CH23ZP": ["53.197727", "-2.884480", "E06000050", "Cheshire West and Chester", "7,928", "3"], "CH23ZQ": ["53.199907", "-2.870393", "E06000050", "Cheshire West and Chester", "27,769", "9"], "CH23ZR": ["53.200110", "-2.869783", "E06000050", "Cheshire West and Chester", "27,769", "9"], "CH23ZS": ["53.202283", "-2.871249", "E06000050", "Cheshire West and Chester", "31,428", "10"], "CH23ZT": ["53.197727", "-2.884480", "E06000050", "Cheshire West and Chester", "7,928", "3"], "CH23ZU": ["53.197727", "-2.884480", "E06000050", "Cheshire West and Chester", "7,928", "3"], "CH23ZW": ["53.200110", "-2.869783", "E06000050", "Cheshire West and Chester", "27,769", "9"], "CH23ZY": ["53.199953", "-2.870229", "E06000050", "Cheshire West and Chester", "27,769", "9"], "CH24AA": ["53.227215", "-2.903213", "E06000050", "Cheshire West and Chester", "20,685", "7"], "CH24AB": ["53.225280", "-2.895113", "E06000050", "Cheshire West and Chester", "20,685", "7"], "CH24AD": ["53.223929", "-2.895445", "E06000050", "Cheshire West and Chester", "20,685", "7"], "CH24AE": ["53.223410", "-2.895239", "E06000050", "Cheshire West and Chester", "20,685", "7"], "CH24AF": ["53.223120", "-2.897854", "E06000050", "Cheshire West and Chester", "20,685", "7"], "CH24AG": ["53.223855", "-2.896941", "E06000050", "Cheshire West and Chester", "20,685", "7"], "CH24AH": ["53.222339", "-2.900115", "E06000050", "Cheshire West and Chester", "20,685", "7"], "CH24AJ": ["53.222645", "-2.899717", "E06000050", "Cheshire West and Chester", "20,685", "7"], "CH24AL": ["53.222732", "-2.901621", "E06000050", "Cheshire West and Chester", "20,685", "7"], "CH24AN": ["53.225280", "-2.895113", "E06000050", "Cheshire West and Chester", "20,685", "7"], "CH24AP": ["53.222394", "-2.898753", "E06000050", "Cheshire West and Chester", "20,685", "7"], "CH24AQ": ["53.224284", "-2.896111", "E06000050", "Cheshire West and Chester", "20,685", "7"], "CH24AR": ["53.222167", "-2.897894", "E06000050", "Cheshire West and Chester", "20,685", "7"], "CH24AS": ["53.221139", "-2.898277", "E06000050", "Cheshire West and Chester", "30,637", "10"], "CH24AT": ["53.224552", "-2.898663", "E06000050", "Cheshire West and Chester", "20,685", "7"], "CH24AU": ["53.224667", "-2.897752", "E06000050", "Cheshire West and Chester", "20,685", "7"], "CH24AW": ["53.224328", "-2.894989", "E06000050", "Cheshire West and Chester", "20,685", "7"], "CH24AX": ["53.224110", "-2.897785", "E06000050", "Cheshire West and Chester", "20,685", "7"], "CH24AY": ["53.224282", "-2.898822", "E06000050", "Cheshire West and Chester", "20,685", "7"], "CH24AZ": ["53.224609", "-2.898305", "E06000050", "Cheshire West and Chester", "20,685", "7"], "CH24BA": ["53.223456", "-2.893787", "E06000050", "Cheshire West and Chester", "20,685", "7"], "CH24BB": ["53.227602", "-2.892316", "E06000050", "Cheshire West and Chester", "20,685", "7"], "CH24BD": ["53.225280", "-2.895113", "E06000050", "Cheshire West and Chester", "20,685", "7"], "CH24BE": ["53.238759", "-2.901718", "E06000050", "Cheshire West and Chester", "20,685", "7"], "CH24BF": ["53.223889", "-2.823862", "E06000050", "Cheshire West and Chester", "26,435", "9"], "CH24BG": ["53.230895", "-2.878677", "E06000050", "Cheshire West and Chester", "20,685", "7"], "CH24BH": ["53.235275", "-2.894063", "E06000050", "Cheshire West and Chester", "20,685", "7"], "CH24BJ": ["53.239818", "-2.891146", "E06000050", "Cheshire West and Chester", "20,685", "7"], "CH24BL": ["53.239469", "-2.889761", "E06000050", "Cheshire West and Chester", "20,685", "7"], "CH24BN": ["53.238116", "-2.885253", "E06000050", "Cheshire West and Chester", "20,685", "7"], "CH24BP": ["53.239557", "-2.868141", "E06000050", "Cheshire West and Chester", "8,513", "3"], "CH24BQ": ["53.240788", "-2.900846", "E06000050", "Cheshire West and Chester", "20,685", "7"], "CH24BR": ["53.236858", "-2.868116", "E06000050", "Cheshire West and Chester", "8,513", "3"], "CH24BS": ["53.240102", "-2.868556", "E06000050", "Cheshire West and Chester", "8,513", "3"], "CH24BT": ["53.241089", "-2.870090", "E06000050", "Cheshire West and Chester", "8,513", "3"], "CH24BU": ["53.225280", "-2.895113", "E06000050", "Cheshire West and Chester", "20,685", "7"], "CH24BW": ["53.229345", "-2.876742", "E06000050", "Cheshire West and Chester", "20,685", "7"], "CH24BX": ["53.241968", "-2.867830", "E06000050", "Cheshire West and Chester", "8,513", "3"], "CH24BY": ["53.241210", "-2.869148", "E06000050", "Cheshire West and Chester", "8,513", "3"], "CH24BZ": ["53.242318", "-2.868900", "E06000050", "Cheshire West and Chester", "8,513", "3"], "CH24DA": ["53.245294", "-2.873621", "E06000050", "Cheshire West and Chester", "8,513", "3"], "CH24DB": ["53.245998", "-2.889416", "E06000050", "Cheshire West and Chester", "20,685", "7"], "CH24DD": ["53.249793", "-2.897543", "E06000050", "Cheshire West and Chester", "20,685", "7"], "CH24DE": ["53.248285", "-2.898201", "E06000050", "Cheshire West and Chester", "20,685", "7"], "CH24DF": ["53.240390", "-2.894964", "E06000050", "Cheshire West and Chester", "20,685", "7"], "CH24DG": ["53.242544", "-2.901692", "E06000050", "Cheshire West and Chester", "20,685", "7"], "CH24DH": ["53.241341", "-2.889515", "E06000050", "Cheshire West and Chester", "20,685", "7"], "CH24DJ": ["53.224358", "-2.830117", "E06000050", "Cheshire West and Chester", "25,493", "8"], "CH24DL": ["53.225634", "-2.830171", "E06000050", "Cheshire West and Chester", "25,493", "8"], "CH24DN": ["53.224963", "-2.830937", "E06000050", "Cheshire West and Chester", "25,493", "8"], "CH24DP": ["53.222034", "-2.828200", "E06000050", "Cheshire West and Chester", "25,493", "8"], "CH24DQ": ["53.220191", "-2.834200", "E06000050", "Cheshire West and Chester", "26,435", "9"], "CH24DR": ["53.221804", "-2.830172", "E06000050", "Cheshire West and Chester", "26,435", "9"], "CH24DS": ["53.223456", "-2.831717", "E06000050", "Cheshire West and Chester", "26,435", "9"], "CH24DT": ["53.224348", "-2.832708", "E06000050", "Cheshire West and Chester", "25,493", "8"], "CH24DU": ["53.223496", "-2.833740", "E06000050", "Cheshire West and Chester", "25,493", "8"], "CH24DW": ["53.223669", "-2.830927", "E06000050", "Cheshire West and Chester", "25,493", "8"], "CH24DX": ["53.225317", "-2.831813", "E06000050", "Cheshire West and Chester", "25,493", "8"], "CH24DY": ["53.224992", "-2.829335", "E06000050", "Cheshire West and Chester", "25,493", "8"], "CH24DZ": ["53.222827", "-2.831720", "E06000050", "Cheshire West and Chester", "26,435", "9"], "CH24EA": ["53.219692", "-2.835299", "E06000050", "Cheshire West and Chester", "26,435", "9"], "CH24EB": ["53.226144", "-2.827440", "E06000050", "Cheshire West and Chester", "26,435", "9"], "CH24ED": ["53.217215", "-2.837227", "E06000050", "Cheshire West and Chester", "26,435", "9"], "CH24EE": ["53.219559", "-2.835011", "E06000050", "Cheshire West and Chester", "26,435", "9"], "CH24EF": ["53.222351", "-2.835590", "E06000050", "Cheshire West and Chester", "26,435", "9"], "CH24EG": ["53.220620", "-2.836245", "E06000050", "Cheshire West and Chester", "26,435", "9"], "CH24EH": ["53.218899", "-2.830386", "E06000050", "Cheshire West and Chester", "26,435", "9"], "CH24EJ": ["53.221834", "-2.828540", "E06000050", "Cheshire West and Chester", "25,493", "8"], "CH24EL": ["53.220348", "-2.830144", "E06000050", "Cheshire West and Chester", "26,435", "9"], "CH24EN": ["53.224931", "-2.818699", "E06000050", "Cheshire West and Chester", "26,435", "9"], "CH24EP": ["53.225638", "-2.832164", "E06000050", "Cheshire West and Chester", "25,493", "8"], "CH24EQ": ["53.221337", "-2.831481", "E06000050", "Cheshire West and Chester", "26,435", "9"], "CH24ER": ["53.214753", "-2.850792", "E06000050", "Cheshire West and Chester", "26,435", "9"], "CH24ES": ["53.216723", "-2.853392", "E06000050", "Cheshire West and Chester", "26,435", "9"], "CH24ET": ["53.211686", "-2.860090", "E06000050", "Cheshire West and Chester", "26,435", "9"], "CH24EU": ["53.213103", "-2.858052", "E06000050", "Cheshire West and Chester", "26,435", "9"], "CH24EW": ["53.223801", "-2.813914", "E06000050", "Cheshire West and Chester", "26,435", "9"], "CH24EX": ["53.213580", "-2.847968", "E06000050", "Cheshire West and Chester", "26,435", "9"], "CH24EY": ["53.221265", "-2.830087", "E06000050", "Cheshire West and Chester", "25,493", "8"], "CH24EZ": ["53.219795", "-2.832065", "E06000050", "Cheshire West and Chester", "26,435", "9"], "CH24FA": ["53.222879", "-2.837203", "E06000050", "Cheshire West and Chester", "26,435", "9"], "CH24FD": ["53.222913", "-2.829789", "E06000050", "Cheshire West and Chester", "26,435", "9"], "CH24FE": ["53.263482", "-2.862178", "E06000050", "Cheshire West and Chester", "8,513", "3"], "CH24FF": ["53.271982", "-2.815294", "E06000050", "Cheshire West and Chester", "19,432", "6"], "CH24FG": ["53.231430", "-2.826089", "E06000050", "Cheshire West and Chester", "26,435", "9"], "CH24FH": ["53.261571", "-2.883697", "E06000050", "Cheshire West and Chester", "19,654", "6"], "CH24GA": ["53.235386", "-2.826330", "E06000050", "Cheshire West and Chester", "25,493", "8"], "CH24GY": ["53.265175", "-2.874387", "E06000050", "Cheshire West and Chester", "2,490", "1"], "CH24GZ": ["53.246654", "-2.857539", "E06000050", "Cheshire West and Chester", "8,513", "3"], "CH24HA": ["53.222214", "-2.855748", "E06000050", "Cheshire West and Chester", "25,493", "8"], "CH24HB": ["53.223326", "-2.856474", "E06000050", "Cheshire West and Chester", "25,493", "8"], "CH24HD": ["53.223118", "-2.853804", "E06000050", "Cheshire West and Chester", "25,493", "8"], "CH24HE": ["53.235816", "-2.846804", "E06000050", "Cheshire West and Chester", "25,493", "8"], "CH24HF": ["53.246964", "-2.859433", "E06000050", "Cheshire West and Chester", "8,513", "3"], "CH24HG": ["53.236015", "-2.849430", "E06000050", "Cheshire West and Chester", "25,493", "8"], "CH24HH": ["53.252286", "-2.867678", "E06000050", "Cheshire West and Chester", "8,513", "3"], "CH24HJ": ["53.252059", "-2.868063", "E06000050", "Cheshire West and Chester", "8,513", "3"], "CH24HL": ["53.251611", "-2.866946", "E06000050", "Cheshire West and Chester", "8,513", "3"], "CH24HN": ["53.260680", "-2.881701", "E06000050", "Cheshire West and Chester", "8,513", "3"], "CH24HP": ["53.253907", "-2.866348", "E06000050", "Cheshire West and Chester", "8,513", "3"], "CH24HQ": ["53.251806", "-2.867294", "E06000050", "Cheshire West and Chester", "8,513", "3"], "CH24HR": ["53.253852", "-2.866541", "E06000050", "Cheshire West and Chester", "8,513", "3"], "CH24HS": ["53.257966", "-2.884957", "E06000050", "Cheshire West and Chester", "8,513", "3"], "CH24HT": ["53.261894", "-2.882955", "E06000050", "Cheshire West and Chester", "8,513", "3"], "CH24HU": ["53.265884", "-2.838283", "E06000050", "Cheshire West and Chester", "8,513", "3"], "CH24HW": ["53.253572", "-2.867960", "E06000050", "Cheshire West and Chester", "8,513", "3"], "CH24HX": ["53.266843", "-2.876175", "E06000050", "Cheshire West and Chester", "2,490", "1"], "CH24HY": ["53.264231", "-2.874353", "E06000050", "Cheshire West and Chester", "2,490", "1"], "CH24HZ": ["53.260279", "-2.880972", "E06000050", "Cheshire West and Chester", "8,513", "3"], "CH24JA": ["53.271247", "-2.858961", "E06000050", "Cheshire West and Chester", "8,400", "3"], "CH24JB": ["53.266193", "-2.837764", "E06000050", "Cheshire West and Chester", "8,513", "3"], "CH24JD": ["53.265017", "-2.837141", "E06000050", "Cheshire West and Chester", "8,513", "3"], "CH24JE": ["53.264598", "-2.836758", "E06000050", "Cheshire West and Chester", "8,513", "3"], "CH24JF": ["53.264435", "-2.837175", "E06000050", "Cheshire West and Chester", "8,513", "3"], "CH24JG": ["53.263350", "-2.835595", "E06000050", "Cheshire West and Chester", "8,513", "3"], "CH24JH": ["53.263265", "-2.838636", "E06000050", "Cheshire West and Chester", "8,513", "3"], "CH24JJ": ["53.263472", "-2.838700", "E06000050", "Cheshire West and Chester", "8,513", "3"], "CH24JL": ["53.240958", "-2.827801", "E06000050", "Cheshire West and Chester", "25,493", "8"], "CH24JN": ["53.256738", "-2.827221", "E06000050", "Cheshire West and Chester", "8,513", "3"], "CH24JP": ["53.245000", "-2.829557", "E06000050", "Cheshire West and Chester", "25,493", "8"], "CH24JQ": ["53.264073", "-2.837618", "E06000050", "Cheshire West and Chester", "8,513", "3"], "CH24JR": ["53.236206", "-2.823574", "E06000050", "Cheshire West and Chester", "25,493", "8"], "CH24JS": ["53.238923", "-2.810994", "E06000050", "Cheshire West and Chester", "15,002", "5"], "CH24JT": ["53.238628", "-2.812413", "E06000050", "Cheshire West and Chester", "15,002", "5"], "CH24JU": ["53.222660", "-2.854049", "E06000050", "Cheshire West and Chester", "25,493", "8"], "CH24JW": ["53.253213", "-2.826179", "E06000050", "Cheshire West and Chester", "25,493", "8"], "CH24JX": ["53.253389", "-2.830213", "E06000050", "Cheshire West and Chester", "25,493", "8"], "CH24JY": ["53.264596", "-2.836099", "E06000050", "Cheshire West and Chester", "8,513", "3"], "CH24JZ": ["53.263903", "-2.875979", "E06000050", "Cheshire West and Chester", "2,490", "1"], "CH24LA": ["53.274355", "-2.813045", "E06000050", "Cheshire West and Chester", "20,309", "7"], "CH24LB": ["53.282051", "-2.788743", "E06000050", "Cheshire West and Chester", "8,400", "3"], "CH24LD": ["53.268129", "-2.821848", "E06000050", "Cheshire West and Chester", "8,513", "3"], "CH24LE": ["53.274097", "-2.813625", "E06000050", "Cheshire West and Chester", "20,309", "7"], "CH24LF": ["53.280151", "-2.814760", "E06000050", "Cheshire West and Chester", "20,309", "7"], "CH24LG": ["53.268826", "-2.822447", "E06000050", "Cheshire West and Chester", "8,513", "3"], "CH24LH": ["53.259745", "-2.826545", "E06000050", "Cheshire West and Chester", "8,513", "3"], "CH24LJ": ["53.268745", "-2.822055", "E06000050", "Cheshire West and Chester", "8,513", "3"], "CH24LL": ["53.268992", "-2.823050", "E06000050", "Cheshire West and Chester", "8,513", "3"], "CH24LN": ["53.271327", "-2.818191", "E06000050", "Cheshire West and Chester", "19,432", "6"], "CH24LP": ["53.273813", "-2.812165", "E06000050", "Cheshire West and Chester", "20,309", "7"], "CH24LQ": ["53.267899", "-2.821319", "E06000050", "Cheshire West and Chester", "8,513", "3"], "CH24LR": ["53.273047", "-2.815090", "E06000050", "Cheshire West and Chester", "19,432", "6"], "CH24LS": ["53.272726", "-2.816058", "E06000050", "Cheshire West and Chester", "19,432", "6"], "CH24LT": ["53.273608", "-2.815835", "E06000050", "Cheshire West and Chester", "19,432", "6"], "CH24LU": ["53.274165", "-2.814181", "E06000050", "Cheshire West and Chester", "20,309", "7"], "CH24LW": ["53.273831", "-2.814820", "E06000050", "Cheshire West and Chester", "20,309", "7"], "CH24LX": ["53.275861", "-2.817588", "E06000050", "Cheshire West and Chester", "20,309", "7"], "CH24LY": ["53.271219", "-2.808982", "E06000050", "Cheshire West and Chester", "20,309", "7"], "CH24LZ": ["53.275331", "-2.816243", "E06000050", "Cheshire West and Chester", "20,309", "7"], "CH24NA": ["53.274457", "-2.814921", "E06000050", "Cheshire West and Chester", "20,309", "7"], "CH24NB": ["53.275890", "-2.818698", "E06000050", "Cheshire West and Chester", "20,309", "7"], "CH24ND": ["53.277038", "-2.816470", "E06000050", "Cheshire West and Chester", "20,309", "7"], "CH24NE": ["53.265008", "-2.875073", "E06000050", "Cheshire West and Chester", "2,490", "1"], "CH24NF": ["53.197727", "-2.884480", "E06000050", "Cheshire West and Chester", "7,928", "3"], "CH24NG": ["53.275310", "-2.811459", "E06000050", "Cheshire West and Chester", "20,309", "7"], "CH24NH": ["53.276199", "-2.815540", "E06000050", "Cheshire West and Chester", "20,309", "7"], "CH24NJ": ["53.279972", "-2.823785", "E06000050", "Cheshire West and Chester", "8,400", "3"], "CH24NL": ["53.281175", "-2.825278", "E06000050", "Cheshire West and Chester", "8,400", "3"], "CH24NN": ["53.281921", "-2.826162", "E06000050", "Cheshire West and Chester", "8,400", "3"], "CH24NP": ["53.283772", "-2.826723", "E06000050", "Cheshire West and Chester", "8,400", "3"], "CH24NQ": ["53.275737", "-2.813131", "E06000050", "Cheshire West and Chester", "20,309", "7"], "CH24NR": ["53.282929", "-2.826422", "E06000050", "Cheshire West and Chester", "8,400", "3"], "CH24NS": ["53.283881", "-2.830400", "E06000050", "Cheshire West and Chester", "8,400", "3"], "CH24NT": ["53.275621", "-2.815904", "E06000050", "Cheshire West and Chester", "20,309", "7"], "CH24NU": ["53.275682", "-2.827977", "E06000050", "Cheshire West and Chester", "8,400", "3"], "CH24NW": ["53.283105", "-2.826996", "E06000050", "Cheshire West and Chester", "8,400", "3"], "CH24NX": ["53.281716", "-2.826339", "E06000050", "Cheshire West and Chester", "8,400", "3"], "CH24NY": ["53.270765", "-2.813637", "E06000050", "Cheshire West and Chester", "8,513", "3"], "CH24NZ": ["53.271780", "-2.813716", "E06000050", "Cheshire West and Chester", "19,432", "6"], "CH24PA": ["53.269153", "-2.821478", "E06000050", "Cheshire West and Chester", "8,513", "3"], "CH24PB": ["53.271018", "-2.814796", "E06000050", "Cheshire West and Chester", "19,432", "6"], "CH24PD": ["53.271739", "-2.814435", "E06000050", "Cheshire West and Chester", "19,432", "6"], "CH24PE": ["53.275430", "-2.817580", "E06000050", "Cheshire West and Chester", "20,309", "7"], "CH24PF": ["53.274668", "-2.816020", "E06000050", "Cheshire West and Chester", "20,309", "7"], "CH24PG": ["53.271267", "-2.817815", "E06000050", "Cheshire West and Chester", "19,432", "6"], "CH24PH": ["53.271377", "-2.816138", "E06000050", "Cheshire West and Chester", "19,432", "6"], "CH24PJ": ["53.272792", "-2.819449", "E06000050", "Cheshire West and Chester", "19,432", "6"], "CH24PL": ["53.271949", "-2.820587", "E06000050", "Cheshire West and Chester", "19,432", "6"], "CH24PN": ["53.271951", "-2.818863", "E06000050", "Cheshire West and Chester", "19,432", "6"], "CH24PP": ["53.272203", "-2.821447", "E06000050", "Cheshire West and Chester", "19,432", "6"], "CH24PQ": ["53.271930", "-2.816733", "E06000050", "Cheshire West and Chester", "19,432", "6"], "CH24PR": ["53.272312", "-2.822663", "E06000050", "Cheshire West and Chester", "19,432", "6"], "CH24PS": ["53.272406", "-2.823355", "E06000050", "Cheshire West and Chester", "19,432", "6"], "CH24PT": ["53.272951", "-2.822481", "E06000050", "Cheshire West and Chester", "19,432", "6"], "CH24PU": ["53.270555", "-2.819301", "E06000050", "Cheshire West and Chester", "19,432", "6"], "CH24PW": ["53.272248", "-2.820158", "E06000050", "Cheshire West and Chester", "19,432", "6"], "CH24PX": ["53.270157", "-2.821063", "E06000050", "Cheshire West and Chester", "8,513", "3"], "CH24PY": ["53.269880", "-2.820727", "E06000050", "Cheshire West and Chester", "8,513", "3"], "CH24PZ": ["53.262579", "-2.883899", "E06000050", "Cheshire West and Chester", "4,967", "2"], "CH24QA": ["53.277139", "-2.820117", "E06000050", "Cheshire West and Chester", "20,309", "7"], "CH24QB": ["53.271800", "-2.811796", "E06000050", "Cheshire West and Chester", "20,309", "7"], "CH24QD": ["53.270624", "-2.811820", "E06000050", "Cheshire West and Chester", "8,513", "3"], "CH24QE": ["53.269904", "-2.810622", "E06000050", "Cheshire West and Chester", "8,513", "3"], "CH24QF": ["53.270487", "-2.810873", "E06000050", "Cheshire West and Chester", "20,309", "7"], "CH24QG": ["53.270702", "-2.808283", "E06000050", "Cheshire West and Chester", "8,513", "3"], "CH24QH": ["53.222169", "-2.833220", "E06000050", "Cheshire West and Chester", "26,435", "9"], "CH24QJ": ["53.224828", "-2.827025", "E06000050", "Cheshire West and Chester", "25,493", "8"], "CH24QL": ["53.224489", "-2.827977", "E06000050", "Cheshire West and Chester", "25,493", "8"], "CH24QN": ["53.224021", "-2.828103", "E06000050", "Cheshire West and Chester", "25,493", "8"], "CH24QP": ["53.221271", "-2.827945", "E06000050", "Cheshire West and Chester", "25,493", "8"], "CH24QQ": ["53.271768", "-2.810267", "E06000050", "Cheshire West and Chester", "20,309", "7"], "CH24QR": ["53.223342", "-2.826143", "E06000050", "Cheshire West and Chester", "25,493", "8"], "CH24QS": ["53.222835", "-2.827976", "E06000050", "Cheshire West and Chester", "25,493", "8"], "CH24QT": ["53.225136", "-2.825444", "E06000050", "Cheshire West and Chester", "25,493", "8"], "CH24QU": ["53.224493", "-2.824862", "E06000050", "Cheshire West and Chester", "25,493", "8"], "CH24QW": ["53.224257", "-2.826505", "E06000050", "Cheshire West and Chester", "25,493", "8"], "CH24QX": ["53.225737", "-2.826953", "E06000050", "Cheshire West and Chester", "25,493", "8"], "CH24QY": ["53.222795", "-2.828664", "E06000050", "Cheshire West and Chester", "25,493", "8"], "CH24QZ": ["53.268279", "-2.802359", "E06000050", "Cheshire West and Chester", "8,513", "3"], "CH24RA": ["53.268759", "-2.873515", "E06000050", "Cheshire West and Chester", "8,513", "3"], "CH24RB": ["53.271558", "-2.841482", "E06000050", "Cheshire West and Chester", "8,400", "3"], "CH24RD": ["53.274308", "-2.809445", "E06000050", "Cheshire West and Chester", "20,309", "7"], "CH24RE": ["53.272817", "-2.811906", "E06000050", "Cheshire West and Chester", "20,309", "7"], "CH24RF": ["53.273445", "-2.813418", "E06000050", "Cheshire West and Chester", "20,309", "7"], "CH24RG": ["53.263359", "-2.874380", "E06000050", "Cheshire West and Chester", "2,490", "1"], "CH24RH": ["53.274887", "-2.810221", "E06000050", "Cheshire West and Chester", "20,309", "7"], "CH24RJ": ["53.272360", "-2.809034", "E06000050", "Cheshire West and Chester", "20,309", "7"], "CH24RL": ["53.271765", "-2.808003", "E06000050", "Cheshire West and Chester", "20,309", "7"], "CH24RN": ["53.271615", "-2.807595", "E06000050", "Cheshire West and Chester", "20,309", "7"], "CH24RP": ["53.273622", "-2.809927", "E06000050", "Cheshire West and Chester", "20,309", "7"], "CH24RQ": ["53.274777", "-2.807910", "E06000050", "Cheshire West and Chester", "20,309", "7"], "CH24RR": ["53.272886", "-2.811023", "E06000050", "Cheshire West and Chester", "20,309", "7"], "CH24RS": ["53.272715", "-2.808396", "E06000050", "Cheshire West and Chester", "20,309", "7"], "CH24RT": ["53.274002", "-2.808150", "E06000050", "Cheshire West and Chester", "20,309", "7"], "CH24RU": ["53.273569", "-2.808472", "E06000050", "Cheshire West and Chester", "20,309", "7"], "CH24RW": ["53.272577", "-2.808888", "E06000050", "Cheshire West and Chester", "20,309", "7"], "CH24RX": ["53.274948", "-2.807928", "E06000050", "Cheshire West and Chester", "20,309", "7"], "CH24RY": ["53.273711", "-2.813933", "E06000050", "Cheshire West and Chester", "20,309", "7"], "CH24SA": ["53.269785", "-2.871856", "E06000050", "Cheshire West and Chester", "8,513", "3"], "CH24SB": ["53.264229", "-2.874697", "E06000050", "Cheshire West and Chester", "2,490", "1"], "CH24TA": ["53.216278", "-2.829871", "E06000050", "Cheshire West and Chester", "26,435", "9"], "CH24TD": ["53.223590", "-2.828979", "E06000050", "Cheshire West and Chester", "26,435", "9"], "CH24TE": ["53.220447", "-2.835343", "E06000050", "Cheshire West and Chester", "26,435", "9"], "CH24TF": ["53.221136", "-2.834443", "E06000050", "Cheshire West and Chester", "26,435", "9"], "CH24TH": ["53.222913", "-2.829789", "E06000050", "Cheshire West and Chester", "26,435", "9"], "CH24TX": ["53.214140", "-2.847530", "E06000050", "Cheshire West and Chester", "26,435", "9"], "CH24WA": ["53.197786", "-2.884632", "E06000050", "Cheshire West and Chester", "7,928", "3"], "CH24WB": ["53.197727", "-2.884480", "E06000050", "Cheshire West and Chester", "7,928", "3"], "CH24WD": ["53.197727", "-2.884480", "E06000050", "Cheshire West and Chester", "7,928", "3"], "CH24WE": ["53.197727", "-2.884480", "E06000050", "Cheshire West and Chester", "7,928", "3"], "CH24WF": ["53.197727", "-2.884480", "E06000050", "Cheshire West and Chester", "7,928", "3"], "CH24WG": ["53.253447", "-2.833873", "E06000050", "Cheshire West and Chester", "8,513", "3"], "CH24WH": ["53.197727", "-2.884480", "E06000050", "Cheshire West and Chester", "7,928", "3"], "CH24WJ": ["53.197727", "-2.884480", "E06000050", "Cheshire West and Chester", "7,928", "3"], "CH24WL": ["53.253456", "-2.833873", "E06000050", "Cheshire West and Chester", "8,513", "3"], "CH24WN": ["53.253456", "-2.833873", "E06000050", "Cheshire West and Chester", "8,513", "3"], "CH24WP": ["53.253456", "-2.833873", "E06000050", "Cheshire West and Chester", "8,513", "3"], "CH24WQ": ["53.253456", "-2.833873", "E06000050", "Cheshire West and Chester", "8,513", "3"], "CH24WR": ["53.253456", "-2.833873", "E06000050", "Cheshire West and Chester", "8,513", "3"], "CH24WS": ["53.197727", "-2.884480", "E06000050", "Cheshire West and Chester", "7,928", "3"], "CH24WT": ["53.197727", "-2.884480", "E06000050", "Cheshire West and Chester", "7,928", "3"], "CH24WU": ["53.197727", "-2.884480", "E06000050", "Cheshire West and Chester", "7,928", "3"], "CH24WW": ["53.253456", "-2.833873", "E06000050", "Cheshire West and Chester", "8,513", "3"], "CH24WX": ["53.253456", "-2.833873", "E06000050", "Cheshire West and Chester", "8,513", "3"], "CH24WY": ["53.197727", "-2.884480", "E06000050", "Cheshire West and Chester", "7,928", "3"], "CH24WZ": ["53.197727", "-2.884480", "E06000050", "Cheshire West and Chester", "7,928", "3"], "CH24XA": ["53.197727", "-2.884480", "E06000050", "Cheshire West and Chester", "7,928", "3"], "CH24XP": ["53.197727", "-2.884480", "E06000050", "Cheshire West and Chester", "7,928", "3"], "CH24XR": ["53.197727", "-2.884480", "E06000050", "Cheshire West and Chester", "7,928", "3"], "CH24YT": ["53.214140", "-2.847530", "E06000050", "Cheshire West and Chester", "26,435", "9"], "CH24ZA": ["53.214140", "-2.847530", "E06000050", "Cheshire West and Chester", "26,435", "9"], "CH24ZB": ["53.197727", "-2.884480", "E06000050", "Cheshire West and Chester", "7,928", "3"], "CH24ZD": ["53.197727", "-2.884480", "E06000050", "Cheshire West and Chester", "7,928", "3"], "CH24ZR": ["53.197727", "-2.884480", "E06000050", "Cheshire West and Chester", "7,928", "3"], "CH24ZT": ["53.197727", "-2.884480", "E06000050", "Cheshire West and Chester", "7,928", "3"], "CH24ZW": ["53.197727", "-2.884480", "E06000050", "Cheshire West and Chester", "7,928", "3"]}